Workbook

Sheet Mudança de Endereço 
N1: R$100,00
N2: R$70,00
N3: RENATA
D4: DATA: | E4: 45667 | N4: KAROLAYNE
D5: VALIDADO POR: | E5: HIAGO | H5: VALOR DA MUDANÇA: | I5: R$100,00 | N5: VICTOR HUGO
B6: VALIDAÇÕES | D6: TIPO DE SERVIÇO | H6: ATENDENTE: | N6: HIAGO
D7: NOME CLIENTE: | E7: ISABELLA SANTOS PAULA | H7: DATA AGENDAMENTO: | I7: =VLOOKUP($E$7,'base de dados'!$C:$I,4,0) -> 46176 | K7: HORA | L7: DIA | N7: IZABELA
B8: CONFERIR ORDEM DE SERVIÇO | D8: TELEFONE CLIENTE: | E8: =VLOOKUP($E$7,'base de dados'!$C:$S,3,0) -> 3499232699 | H8: HORA AGENDAMENTO: | I8: =VLOOKUP($E$7,'base de dados'!$C:$I,6,0) -> 0.41666667 | K8: =NOW() -> 46192.688 | L8: =TODAY() -> 46192 | N8: VITOR SILVA
B9: CONFERIR PROTOCOLO | D9: NOVO ENDEREÇO: | H9: FORMA DE PAGAMENTO: | I9: =VLOOKUP($E$7,'base de dados'!$C:$I,7,0) -> PIX
B10: CONFERIR SE ENDEREÇO NA ORDEM DE SERVIÇO E CADASTRO FORAM ALTERADOS | D10: =VLOOKUP($E$7,'base de dados'!$C:$J,8,0) -> ENDEREÇO NOVO: RUA JOSÉ VICENTE DA SILVA, 82 COMPLEMENTO: CASA UNICA CEP: 38425612 BAIRRO: SHOPPING PARK | H10: QUEM ACOMPANHA? | N10: MUD END
B11: CONFERIR EM PESSOAS E EMPRESAS SE POSSUI OUTRA INSTALAÇÃO ATIVA NO MESMO ENDEREÇO | H11: NOME: | I11: =VLOOKUP($E$7,'base de dados'!$C:$S,13,0) -> BERNADETE SANTOS PAULA (AVO) | N11: MUD END + ALT PLAN
B12: CONFERIR FINANCEIRO | H12: TELEFONE: | I12: =VLOOKUP($E$7,'base de dados'!$C:$S,14,0) -> 3499232699
B13: CONFERIR SE O CLIENTE TEM OU NÃO FIDELIDADE (SE NÃO TIVER, É RESPONSABILIDADE DO ATENDENTE OFERTAR E TER INFORMAÇÃO NO PROTOCOLO) | H13: OBSERVAÇÕES | N13: CARTÃO
B14: CASO SEJA COM ALTERAÇÃO DE PLANO: VERIFICAR NOVO PLANO E ROTEADOR, SE FOR PARA TROCAR EQUIPAMENTO PRECISA ESTAR NA O.S/PROTOCOLO E AGENDA EXCEL – ALTERAR OU ENVIAR PARA FINANCEIRO | D14: EQUIPAMENTO: | E14: =VLOOKUP($E$7,'base de dados'!$C:$K,9,0) -> <b>ONT = ONT TP LINK 230 // CONECTOR = VERDE.</b> | H14: =VLOOKUP($E$7,'base de dados'!$C:$S,2,0) -> VALIDAÇÃO OK | N14: DINHEIRO
B15: CONFERIR SE O “TIPO DE O.S” ESTÁ CORRETO | D15: TEXTO PROTOCOLO CONTATO FEITO: | E15: acompanhamento titular | N15: PIX
B16: CASO O CLIENTE TENHA SIDO INSTALADO COM MENOS DE 90 DIAS, PRECISA TER AUTORIZAÇÃO DO HIAGO/DEIVIT | D16: =CONCATENATE("TÉC. ",$E$5," ENTREI EM CONTATO COM ",$E$7," (",$E$8,") DIA ",TEXT(TODAY(),"DD/MM")," ÀS ",TEXT(NOW(),"HH:MM")," HORAS POR LIGAÇÃO . CONFIRMEI OS DADOS ABAIXO: ",$D$10," TAXA A SER PAGA NO MOMENTO DA INSTALAÇÃO DE ",$I$5," NO ",$I$9," E RESSALTEI QUE OS EQUIPAMENTOS DE INTERNET DEVEM SER LEVADOS PARA O NOVO ENDEREÇO, ONU, ROTEADOR OU ONT + (FONTES DE ENERGIA). ",$E$7," VAI ACOMPANHAR A VISITA. CONFIRMADO PARA DIA ",TEXT($I$7,"DD/MM")," ÁS ",TEXT($I$8,"HH:MM")," HORAS.") -> TÉC. HIAGO ENTREI EM CONTATO COM ISABELLA SANTOS PAULA (3499232699) DIA 19/06 ÀS 16:31 HORAS POR LIGAÇÃO . CONFIRMEI OS DADOS ABAIXO: ENDEREÇO NOVO: RUA JOSÉ VICENTE DA SILVA, 82 COMPLEMENTO: CASA UNICA CEP: 38425612 BAIRRO: SHOPPING PARK TAXA A SER PAGA NO MOMENTO DA INSTALAÇÃO DE R$100,00 NO PIX E RESSALTEI QUE OS EQUIPAMENTOS DE INTERNET DEVEM SER LEVADOS PARA O NOVO ENDEREÇO, ONU, ROTEADOR OU ONT + (FONTES DE ENERGIA). ISABELLA SANTOS PAULA VAI ACOMPANHAR A VISITA. CONFIRMADO PARA DIA 03/06 ÁS 10:00 HORAS. | H16: TEXTO PROTOCOLO SEM CONTATO: | N16: MENSALIDADE VINCENDA
B17: **ANTECIPAÇÕES** - VALIDAR DADOS NA LIGAÇÃO - ENVIAR NO GRUPO "TREINAMENTO" - INFORMAR QUE SE SURGIR VAGA QUE ENTRAREMOS EM CONTATO PARA - INFORMAR E VERIFICAR DISPONIBILIDADE DO CLIENTE | H17: =CONCATENATE("TÉC. ",$E$5," TENTEI CONTATO COM ",E7," POR LIGAÇÃO (",E8,") DIA ",TEXT(TODAY(),"DD/MM")," ÀS ",TEXT(K8,"HH:MM"),"HORAS, TELEFONE NÃO ATENDE. ENVIEI MENSAGEM WHATSAPP AGUARDANDO RETORNO.") -> TÉC. HIAGO TENTEI CONTATO COM ISABELLA SANTOS PAULA POR LIGAÇÃO (3499232699) DIA 19/06 ÀS 16:31HORAS, TELEFONE NÃO ATENDE. ENVIEI MENSAGEM WHATSAPP AGUARDANDO RETORNO. | N17: ISENTO
N19: 0.35416667
N20: 0.4375
N21: 0.5625
B22: - VERIFICAR SE MUDANÇA ESTÁ SAINDO DE RESIDENCIAL PARA COMERCIO, OU VICE VERSA E SE POSSUI AUTORIZAÇÃO PARA PROSSEGUIR. | N22: 0.64583333
N23: A PARTIR DAS 11:00
B28: ALTERAÇÃO DE PLANO? | D28: TEXTO PROTOCOLO CONTATO FEITO: | E28: (acompanhamento terceiros
B29: =VLOOKUP($E$7,'base de dados'!$C:$M,11,0) -> - | D29: =CONCATENATE("TÉC. ",$E$5," ENTREI EM CONTATO COM ",$E$7," (",$E$8,") DIA ",TEXT(TODAY(),"DD/MM")," ÀS ",TEXT(NOW(),"HH:MM")," HORAS POR LIGAÇÃO. CONFIRMEI OS DADOS ABAIXO: ",$D$10," TAXA A SER PAGA NO MOMENTO DA INSTALAÇÃO DE R$100,00 NO ",$I$9," E RESSALTEI QUE OS EQUIPAMENTOS DE INTERNET DEVEM SER LEVADOS PARA O NOVO ENDEREÇO, ONU, ROTEADOR OU ONT + (FONTES DE ENERGIA).",$E$7," AUTORIZA ",$I$11, " (",$I$12,") ACOMPANHAR A VISITA. CONFIRMADO PARA DIA ",TEXT($I$7,"DD/MM")," ÁS ",TEXT($I$8,"HH:MM")," HORAS.") -> TÉC. HIAGO ENTREI EM CONTATO COM ISABELLA SANTOS PAULA (3499232699) DIA 19/06 ÀS 16:31 HORAS POR LIGAÇÃO. CONFIRMEI OS DADOS ABAIXO: ENDEREÇO NOVO: RUA JOSÉ VICENTE DA SILVA, 82 COMPLEMENTO: CASA UNICA CEP: 38425612 BAIRRO: SHOPPING PARK TAXA A SER PAGA NO MOMENTO DA INSTALAÇÃO DE R$100,00 NO PIX E RESSALTEI QUE OS EQUIPAMENTOS DE INTERNET DEVEM SER LEVADOS PARA O NOVO ENDEREÇO, ONU, ROTEADOR OU ONT + (FONTES DE ENERGIA).ISABELLA SANTOS PAULA AUTORIZA BERNADETE SANTOS PAULA (AVO) (3499232699) ACOMPANHAR A VISITA. CONFIRMADO PARA DIA 03/06 ÁS 10:00 HORAS.

Sheet base de dados
A1: TEXTO AGENDA | B1: TIPO DE MUDANÇA | C1: NOME | D1: CONFERENCIA SISTEMA | E1: TELEFONE | F1: DATA MUDANÇA | G1: DIA DA SEMANA | H1: HORARIO MUDANÇA | I1: FORMA DE PAGAMENTO | J1: NOVO ENDEREÇO | K1: EQUIPAMENTO | L1: ALTERAÇÃO DE PLANO | M1: PLANO ESCOLHIDO | N1: TITULAR ACOMPANHA? | O1: NOME + GRAU DE PARENTESCO | P1: TELEFONE TERCEIRO | Q1: TEXTO COMPROVANTE DE ENDEREÇO | R1: CONFERENCIA END, COMPROVANTE | S1: PRAZO VALIDAÇÃO OK? | Y1: MUD END + ALT PLAN
A2: 10/04 MUD END CARLOS AUGUSTO RODRIGUES DE MATTOS PROT:2603.33782 CARTAO (GABRIEL M.) - LAGOINHA | B2: MUD END | D2: VALIDADO | E2: 34988647760 | F2: 46032 | G2: =PROPER(TEXT(F2,"DDD")) -> Sáb | H2: 0.33333333 | I2: CARTÃO | J2: ENDEREÇO NOVO: RUA BENTO DE FARIA, 80 COMPLEMENTO: CASA UNICA CEP: 38408514 BAIRRO: LAGOINHA | K2: <b>ONU = DATA // CONECTOR = VERDE.</b> | L2: =IF(B2="MUD END","NÃO","SIM") -> NÃO | N2: SIM | O2: - | P2: - | Q2: COMPROVANTE DE ENDEREÇO (CEMIG) EM ANEXO NOME NO COMPROVANTE: MARIA HELENA VASCONCELOS DE OLIVEIRA (DISSE SER PRIMA DO ASSINANTE.) | S2: =IF(F2<TODAY(),"EXECUTADA",IF(F2=TODAY(),"EM EXECUÇÃO",IF(F2=TODAY()+1,"VALIDAR HOJE",IF(F2>TODAY()+1,"VALIDAR DEPOIS","-")))) -> EXECUTADA
A3: MUD END ENEIAS RODRIGUES DE SOUZA (NOVO VISUAL SERVICOS GRAFICA) PROT:2603.1107 PIX (HALYSON) - OSVALDO REZENDE **(POSSUI WI-FI EXTEND)** *PENDENTE COMPROVANTE PAGAMENTO E ENDEREÇO* | B3: MUD END | E3: 34992322706 | F3: 46114 | G3: =PROPER(TEXT(F3,"DDD")) -> Qui | H3: 0.33333333 | I3: PIX | J3: ENDEREÇO NOVO: RUA ANTÔNIO THOMAZ DE REZENDE, 201 COMPLEMENTO: SALA 5 REFERÊNCIA: GALPÃO CEP: 38400487 BAIRRO: OSVALDO REZENDE | K3: <b>ONT = ONT TP LINK 530 // CONECTOR = VERDE.</b> | L3: =IF(B3="MUD END","NÃO","SIM") -> NÃO | M3: - | N3: sim | S3: =IF(F3<TODAY(),"EXECUTADA",IF(F3=TODAY(),"EM EXECUÇÃO",IF(F3=TODAY()+1,"VALIDAR HOJE",IF(F3>TODAY()+1,"VALIDAR DEPOIS","-")))) -> EXECUTADA
A4: MUD END + ALT PLANO LUCAS FERREIRA GOMES PROT:2603.34716 ISENTO (JHONATAN) - DANIEL FONSECA | B4: MUD END + ALT PLAN | D4: VALIDAÇÃO OK ENVIAR AO CADASTRO selfie pendente de documento | E4: 34991631067 | F4: 46114 | G4: =PROPER(TEXT(F4,"DDD")) -> Qui | H4: 0.33333333 | I4: ISENTO | J4: ENDEREÇO NOVO: RUA VARGINHA, 1155 COMPLEMENTO: COND. MARANATA, APT 203 CEP: 38400322 BAIRRO: DANIEL FONSECA | K4: . <b>ONT = ONT ZTE // CONECTOR = VERDE.</b> | L4: =IF(B4="MUD END","NÃO","SIM") -> SIM | M4: PLANO ATUAL: 1000 MEGA/99,90 CONTRATADO EM 07/2025 COM FIDELIDADE DE 12 MESES. ROTEADOR: ONT ZTE F 670-L PLANO SOLICITADO: 1 GIGA (1.000 MEGA) R$99,90. BENEFÍCIOS: ACESSO GRATUITO AO APP MZTV (CDNTV+) + VOD | N4: NÃO | O4: DOUGLAS FERNANDES BORGES. (INQUILINO) | P4: 64 9328-2617 | Q4: COMPROVANTE DE ENDEREÇO (CONTRATO DE LOCAÇÃO) EM ANEXO NOME NO COMPROVANTE: DOUGLAS FERNANDES BORGES (INQUILINO) | R4: MK END: N/C ___________________________ MK NOMES: -> SOCRATES RODRIGUES QUEIROZ - CPF: 052.678.796-14 - LOCADOR DO IMÓVEL - CLIENTE ATIVO NO ENDEREÇO: RUA SEBASTIAO DE FREITAS, 287. ADIMPLENTE COM EMPRESA; -> POLIANA EVANGELISTA SILVA - CPF: 059.825.136-79 - LOCATÁRIA DO IMÓVEL - N/C ; -> DOUGLAS FERNANDES BORGES - CPF: 056.809.281-26 - LOCATÁRIO DO IMÓVEL - N/C ; -> LUCAS FERREIRA GOMES - CPF: 065.584.586-08 - CLIENTE ATIVO E ADIMPLENTE COM A EMPRESA. | S4: =IF(F4<TODAY(),"EXECUTADA",IF(F4=TODAY(),"EM EXECUÇÃO",IF(F4=TODAY()+1,"VALIDAR HOJE",IF(F4>TODAY()+1,"VALIDAR DEPOIS","-")))) -> EXECUTADA
A5: MUD END + ALT PLANO EDUARDO APARECIDO DA SILVA PROT:2603.34636 ISENTO (JOSÉ Jr) - JARDIM BOTÂNICO **PRÉDIO COM PRUMADA** // *TROCA DE EQUIPAMENTO* | B5: MUD END + ALT PLAN | D5: VALIDAÇÃO OK ENVIAR AO CADASTRO | E5: 34998684694 | F5: 46114 | G5: =PROPER(TEXT(F5,"DDD")) -> Qui | H5: 0.41666667 | I5: ISENTO | J5: ENDEREÇO NOVO: AVENIDA VEREADOR CARLITO CORDEIRO, 1895 COMPLEMENTO: CONDOMINIO RESIDENCIAL PARK KARAIBA BL-A APT 109 CEP: 38410665 BAIRRO: JARDIM BOTÂNICO | K5: <b>ONU = DATA // CONECTOR = VERDE.</b> | L5: =IF(B5="MUD END","NÃO","SIM") -> SIM | M5: PLANO ATUAL: 500 MEGA/79,90 CONTRATADO EM 04/2024 COM FIDELIDADE DE 12 MESES. ROTEADOR: GREATEK PLANO OFERTADO: 600 MEGA/79,90. BENEFÍCIOS: ACESSO GRATUITO AO APP MZTV (CDNTV+) | N5: SIM | O5: - | P5: - | Q5: COMPROVANTE DE ENDEREÇO (TAXA DE CONDOMINIO ) EM ANEXO NOME NO COMPROVANTE: ALINE CAREN CARDOSO (CLIENTE DIZ QUE É SUA ESPOSA) | R5: MK END:N/C MK NOMES: ALINE CAREN CARDOSO CPF:***.619.116-**(CLIENTE DIZ QUE É SUA ESPOSA)N/C SCHWARTZ COBRE LTDA CNPJ:18.450.750/0001-20(EMPRESA RESPONSÁVEL PELO RECEBIMENTO DOS VALORES DA TAXA DE CONDOMÍNIO)N/C | S5: =IF(F5<TODAY(),"EXECUTADA",IF(F5=TODAY(),"EM EXECUÇÃO",IF(F5=TODAY()+1,"VALIDAR HOJE",IF(F5>TODAY()+1,"VALIDAR DEPOIS","-")))) -> EXECUTADA
A6: MUD END + ALT PLANO JULIA GABRIELA MARIA DORNELES PROT:2603.35607 ISENTO (BRUNA) - LARANJEIRAS // *ASSINATURA PEND* | B6: MUD END + ALT PLAN | D6: VALIDAÇÃO OK ENVIAR AO CADASTRO PENDENTE ASSINATURA DO CONTRATO | E6: 34984190334 | F6: 46114 | G6: =PROPER(TEXT(F6,"DDD")) -> Qui | H6: 0.54166667 | I6: ISENTO | J6: ENDEREÇO NOVO: RUA DAS DIRETAS, 165 COMPLEMENTO: CASA 2 CEP: 38410492 BAIRRO: LARANJEIRAS | K6: <b>ONT = ONT TP LINK 530 // CONECTOR = VERDE.</b> | L6: =IF(B6="MUD END","NÃO","SIM") -> SIM | M6: PLANO ATUAL: 1000 MEGA/99,90 CONTRATADO EM 05/25 COM FIDELIDADE DE 12 MESES. ROTEADOR: ONT TP-LINK X530 PLANO OFERTADO: 1 GIGA (1.000 MEGA) R$99,90. BENEFÍCIOS: ACESSO GRATUITO AO APP MZTV (CDNTV+) + VOD | N6: SIM | O6: - | P6: - | Q6: COMPROVANTE DE ENDEREÇO (CEMIG) EM ANEXO NOME NO COMPROVANTE: VINICIUS RIBEIRO SANTOS (DIZ SER ANTIGO INQUILINO) | R6: MK END: N/C MK NOMES: VINICIUS RIBEIRO SANTOS (ANTIGO INQUILINO): HAVIA REALIZADO PEDIDO DE INSTALAÇÃO EM 17/03/2023, PORÉM, A FICHA FOI REPROVADA DEVIDO AO SCORE BAIXO E RESTRIÇÕES. | S6: =IF(F6<TODAY(),"EXECUTADA",IF(F6=TODAY(),"EM EXECUÇÃO",IF(F6=TODAY()+1,"VALIDAR HOJE",IF(F6>TODAY()+1,"VALIDAR DEPOIS","-")))) -> EXECUTADA
A7: MUD END + ALT PLANO DENISE DE FREITAS PROT:2603.22413 ISENTO (ANDREZA) - JARDIM DAS PALMEIRAS // *LIGAR QUANDO ESTIVER A CAMINHO* | B7: MUD END + ALT PLAN | D7: VALIDAÇÃO OK ENVIAR AO CADASTRO | E7: (34) 99987-1906 | F7: 46114 | G7: =PROPER(TEXT(F7,"DDD")) -> Qui | H7: 0.54166667 | I7: ISENTO | J7: ENDEREÇO NOVO: RUA DO TOPÓGRAFO, 80 COMPLEMENTO: CASA ÚNICA CEP: 38412280 BAIRRO: JARDIM DAS PALMEIRAS | K7: <b>ONT = ONT TP LINK 230 // CONECTOR = VERDE.</b> | L7: =IF(B7="MUD END","NÃO","SIM") -> SIM | M7: PLANO ATUAL: 600 MEGA/79,90 CONTRATADO EM 07/2025 COM FIDELIDADE DE 12 MESES. ROTEADOR: ONT TP-LINK XC230 PLANO OFERTADO: 600 MEGA/79,90. BENEFÍCIOS: ACESSO GRATUITO AO APP MZTV (CDNTV+) | N7: SIM | O7: - | P7: - | Q7: COMPROVANTE DE ENDEREÇO (CEMIG) EM ANEXO NOME NO COMPROVANTE: DENISE DE FREITAS AMARAL (ASSINANTE) | R7: MK END: -> AMARILDO ROBERTO SILVA (EX ESPOSO DA ASSINANTE) - CPF 739.538.576-49: CONEXÃO ATIVA DESDE 10/2020 E ADIMPLENTE COM A EMPRESA. >>> ESTÁ COM MUDANÇA DE ENDEREÇO AGENDADA PARA 01/04. ________________________________________ MK NOMES: -> DENISE DE FREITAS AMARAL - CPF 059.756.676-31: ASSINANTE DA CONEXÃO. | S7: =IF(F7<TODAY(),"EXECUTADA",IF(F7=TODAY(),"EM EXECUÇÃO",IF(F7=TODAY()+1,"VALIDAR HOJE",IF(F7>TODAY()+1,"VALIDAR DEPOIS","-")))) -> EXECUTADA
A8: MUD END + ALT PLANO BRUNA DA SILVA GUMERATO PROT:2603.32071 ISENTO (RONALD) - LOTEAMENTO RESIDENCIAL PEQUIS // *CLIENTE CONTRATOU PLANO WI-FI EXTEND* | B8: MUD END + ALT PLAN | D8: OS ERRADA CASO SEJA APROVADO O EXTEND PARA CASA FRENTE DA MÃE .. SERÁ NECESSÁRIO GERAR 2 OS | E8: 34992354684 | F8: 46114 | G8: =PROPER(TEXT(F8,"DDD")) -> Qui | H8: 0.54166667 | I8: ISENTO | J8: ENDEREÇO NOVO: RUA DO AZULÃO, 176 COMPLEMENTO: CASA FUNDOS CEP: 38421040 BAIRRO: LOTEAMENTO RESIDENCIAL PEQUIS | K8: <b>ONT = ONT TP LINK 230 // CONECTOR = VERDE.</b> | L8: =IF(B8="MUD END","NÃO","SIM") -> SIM | M8: PLANO ATUAL: 600 MEGA/79,90 CONTRATADO EM 01/2025 COM FIDELIDADE DE 12 MESES. ROTEADOR: ONT TP-LINK XC230 PLANO OFERTADO: 1 GIGA (1.000 MEGA); + WI-FI EXTEND (ROTEADOR ADICIONAL) MENSALIDADE: R$134,90; EQUIPAMENTOS EMPRESTADOS EM REGIME DE COMODATO + INSTALAÇÃO/ATIVAÇÃO GRÁTIS; BENEFÍCIOS: ACESSO GRATUITO AO APP MZTV (CDNTV+) + VOD | N8: SIM | O8: - | P8: - | Q8: COMPROVANTE DE ENDEREÇO (CEMIG) EM ANEXO NOME NO COMPROVANTE: ANA PAULA DA SILVA (MAE DE BRUNA) | S8: =IF(F8<TODAY(),"EXECUTADA",IF(F8=TODAY(),"EM EXECUÇÃO",IF(F8=TODAY()+1,"VALIDAR HOJE",IF(F8>TODAY()+1,"VALIDAR DEPOIS","-")))) -> EXECUTADA
A9: MUD END + ALT PLANO RAFFAEL SOUZA PIRES PROT:2603.35843 ISENTO (VICTOR H.) - OSVALDO REZENDE **PRÉDIO SEM PRUMADA - ENVIAR TÉCNICO DUPLADO** // *TROCA DE EQUIPAMENTO* | B9: MUD END + ALT PLAN | D9: VALIDAÇÃO OK ENVIAR AO CADASTRO pendente selfie | E9: 34988066015 | F9: 46114 | G9: =PROPER(TEXT(F9,"DDD")) -> Qui | H9: 0.625 | I9: ISENTO | J9: ENDEREÇO NOVO: RUA TAPUIRAMA, 447 COMPLEMENTO: APTO 301 CEP: 38400436 BAIRRO: OSVALDO REZENDE | K9: <b>ONU = DATA // CONECTOR = VERDE.</b> | L9: =IF(B9="MUD END","NÃO","SIM") -> SIM | M9: PLANO ATUAL: 400 MEGA/79,90 CONTRATADO EM 01/2023 COM FIDELIDADE DE 12 MESES. ROTEADOR: GREATEK PLANO OFERTADO: 600 MEGA/79,90. BENEFÍCIOS: ACESSO GRATUITO AO APP MZTV (CDNTV+) | N9: SIM | O9: - | P9: - | Q9: COMPROVANTE DE ENDEREÇO (CONTRATO DE LOCAÇÃO) EM ANEXO NOME NO COMPROVANTE: RAFFAEL SOUZA PIRES (ASSINANTE) | R9: MK NOMES: RAFFAEL SOUZA PIRES CPF: 108.562.846-96 (LOCATÁRIO) ASSINANTE - CONTRATOU EM 01/2023 CONEXÃO ATIVA E ADIMPLENTE DANIELLY PIRES VILELA CPF: 064.549.751-77 (LOCATÁRIA) CONEXÃO CANCELADA EM 04/2024 - QUITOU OS DÉBITOS COM A EMPRESA APÓS ACORDO SUELY FRANCISCA DE SOUZA CPF: 578.091.786-87 (FIADORA) - N/C DIJANIRA FRANCISCA DE OLIVEIRA CPF: 460.756.906-20 (FIADORA) - N/C SANTA FELICIA HOLDING PATRIMONIAL LTDA CNPJ: 22.579.858/0001-95 (LOCADORA) - N/C RGV NEGÓCIOS IMOBILIÁRIOS LTDA CNPJ: 17.808.663/0001-30 (ADMINISTRADORA) - N/C MK END: N/C | S9: =IF(F9<TODAY(),"EXECUTADA",IF(F9=TODAY(),"EM EXECUÇÃO",IF(F9=TODAY()+1,"VALIDAR HOJE",IF(F9>TODAY()+1,"VALIDAR DEPOIS","-")))) -> EXECUTADA
A10: MUD END THIAGO WILKER MELO MIRANDA PROT:2603.35688 CARTAO (RONALD) - TUBALINA **PRÉDIO COM PRUMADA** | B10: MUD END | D10: VALIDAÇÃO OK ENVIAR AO CADASTRO | E10: 34991455433 | F10: 46114 | G10: =PROPER(TEXT(F10,"DDD")) -> Qui | H10: 0.625 | I10: CARTÃO | J10: ENDEREÇO NOVO: RUA VOLUNTÁRIOS DA PÁTRIA, 566 COMPLEMENTO: APT. 201 CEP: 38412072 BAIRRO: TUBALINA | K10: <b>ONT = ONT TP LINK 530 // CONECTOR = VERDE.</b> | L10: =IF(B10="MUD END","NÃO","SIM") -> NÃO | M10: - | N10: SIM | O10: - | P10: - | Q10: COMPROVANTE DE ENDEREÇO (DMAE) EM ANEXO NOME NO COMPROVANTE: THIAGO WILKER MELO MIRANDA (ASSINANTE) | R10: MK END; N/C MK NOME; THIAGO WILKER MELO MIRANDA 015.929.236-07 (ASSINANTE) CONEXÃO ATIVA E CLIENTE ADIMPLENTE | S10: =IF(F10<TODAY(),"EXECUTADA",IF(F10=TODAY(),"EM EXECUÇÃO",IF(F10=TODAY()+1,"VALIDAR HOJE",IF(F10>TODAY()+1,"VALIDAR DEPOIS","-")))) -> EXECUTADA
A11: MUD END RANGEL DE JESUS SOUSA PROT:2603.35872 PIX (VICTOR H.) - GUARANI | B11: MUD END | D11: VALIDAÇÃO OK ENVIAR AO CADASTRO | E11: 34998086440 | F11: 46114 | G11: =PROPER(TEXT(F11,"DDD")) -> Qui | H11: 0.70833333 | I11: PIX | J11: ENDEREÇO NOVO: RUA DA MAZURKA, 582 COMPLEMENTO: CASA FRENTE CEP: 38415417 BAIRRO: GUARANI | K11: <b>ONU = DATA // CONECTOR = VERDE.</b> | L11: =IF(B11="MUD END","NÃO","SIM") -> NÃO | M11: - | N11: SIM | O11: - | P11: - | Q11: COMPROVANTE DE ENDEREÇO (CEMIG) EM ANEXO NOME NO COMPROVANTE: JORCELINO PEREIRA MACEDO FILHO (DISSE SER PROPRIETÁRIO DO IMÓVEL ) | R11: MK END MARIA GLORIA MACEDO (CASA FUNDOS) CANCELOU EM 04/2024, NÃO POSSUI DÉBITOS COM A EMPRESA MK NOMES JORCELINO PEREIRA MACEDO FILHO (DISSE SER PROPRIETÁRIO DO IMÓVEL) - N/C | S11: =IF(F11<TODAY(),"EXECUTADA",IF(F11=TODAY(),"EM EXECUÇÃO",IF(F11=TODAY()+1,"VALIDAR HOJE",IF(F11>TODAY()+1,"VALIDAR DEPOIS","-")))) -> EXECUTADA
A12: MUD END SUIANI TERTO DA SILVA (ESCRITORIO DE ADVOCACIA UNID02) PROT:2603.34007 PIX (ANDREZA) - LUIZOTE DE FREITAS // *ANÁLISE DE 90 DIAS* | B12: MUD END | D12: JA VALIDADO PELO CADASTRO | E12: 64996012416 | F12: 46114 | G12: =PROPER(TEXT(F12,"DDD")) -> Qui | H12: 0.70833333 | I12: PIX | J12: ENDEREÇO NOVO: RUA MATHEUS VAZ, 420 COMPLEMENTO: COMÉRCIO FRENTE CEP: 38414308 BAIRRO: LUIZOTE DE FREITAS | K12: <b>ONT = ONT TP LINK 530 // CONECTOR = VERDE.</b> | L12: =IF(B12="MUD END","NÃO","SIM") -> NÃO | M12: - | N12: SIM | O12: DALILA (ASSESSORA JURÍDICA DE SUIANI) | P12: 64999808642 | Q12: COMPROVANTE DE ENDEREÇO (CONTRATO DE LOCAÇÃO) EM ANEXO NOME NO COMPROVANTE: SUIANI TERTO DA SILVA (ASSINANTE) | R12: MK END: N/C ________________________________________ MK NOMES: -> ROSANGELA RAMILA DE SOUZA (LOCADORA) - CPF 539.306.656-20: N/C -> DELTA IMÓVEIS E ADMINISTRAÇÃO LTDA (PROCURADORA) - CNPJ 23.976.590/0001-98: N/C -> FRANCIS HEME CESAR PEREIRA (REPRESENTANTE) - CPF 086.429.536-75: N/C -> SUIANI TERTO DA SILVA SOCIEDADE INDIVIDUAL DE ADVOCACIA / SUIANI TERTO DA SILVA (LOCATÁRIA/FIADORA) - CNPJ 51.678.451/0001-13 // 032.711.821-08: ASSINANTE DA CONEXÃO. :. POSSUI OUTRAS DUAS CONEXÕES ATIVAS E ADIMPLENTE COM A EMPRESA.: ::. POSSUI UMA SOLICITAÇÃO DE ADESÃO DO ESCRITÓRIO EM SEU CPF APROVADA PARA O CNPJ .:: -> VALERIA CRISTINA FERREIRA DE CARVALHO (TESTEMUNHA): N/C -> RHAYANNE MYCHELLE INÁCIO DE PAULA (TESTEMUNHA): CONEXÃO ATIVA DESDE 11/2025 E ADIMPLENTE COM A EMPRESA. -> DALILA TERTO (ASSESSORA JURÍDICA): N/C | S12: =IF(F12<TODAY(),"EXECUTADA",IF(F12=TODAY(),"EM EXECUÇÃO",IF(F12=TODAY()+1,"VALIDAR HOJE",IF(F12>TODAY()+1,"VALIDAR DEPOIS","-")))) -> EXECUTADA
A13: MUD END + ALT PLANO LUCIEUDA GONCALVES DO NASCIMENTO PROT:2603.34925 ISENTO (LUIS) - GUARANI // | B13: MUD END + ALT PLAN | D13: VALIDAÇÃO OK ENVIAR AO CADASTRO pendente selfie | E13: 34991777444 | F13: 46115 | G13: =PROPER(TEXT(F13,"DDD")) -> Sex | H13: 0.41666667 | I13: ISENTO | J13: ENDEREÇO NOVO: RUA DO BALLET, 784 COMPLEMENTO: CASA ÚNICA CEP: 38415408 BAIRRO: GUARANI | K13: <b>ONU = DATA // CONECTOR = VERDE.</b> | L13: =IF(B13="MUD END","NÃO","SIM") -> SIM | M13: PLANO ATUAL: 250 MEGA/69,90 CONTRATADO EM 07/2023 COM FIDELIDADE DE 12 MESES. ROTEADOR: GREATEK PLANO OFERTADO: 300 MEGA/69,90. BENEFÍCIOS: ACESSO GRATUITO AO APP MZTV (CDNTV+) | N13: SIM | O13: - | P13: - | Q13: COMPROVANTE DE ENDEREÇO (CONTRATO DE LOCAÇÃO) EM ANEXO NOME NO COMPROVANTE: ANGELICA GONCALVES PEREIRA (LUCIEUDA ALEGA SER SUA FILHA) | R13: MK END: N/C MK NOMES: - ALESSANDRA DE MELO BELELLI - LOCADORA - N/C - ANGELICA GONÇALVES PEREIRA - CPF 614.285.203-76 - LOCATÁRIA (FILHA) - FICHA CADASTRAL REALIZADA EM 26/07/2023 ONDE FOI NEGADA EM SEU NOME E APROVADO NO NOME DA MÃE LUCIEUDA GONCALVES DO NASCIMENTO. INSTALDO EM RUA AGENOR BORGES, 280 - APTO 01. - LUCIEUDA GONCALVES DO NASCIMENTO - CPF 039.937.403-51 - ASSINANTE - CLIENTE ATIVA E ADIMPLENTE COM A EMPRESA. | S13: =IF(F13<TODAY(),"EXECUTADA",IF(F13=TODAY(),"EM EXECUÇÃO",IF(F13=TODAY()+1,"VALIDAR HOJE",IF(F13>TODAY()+1,"VALIDAR DEPOIS","-")))) -> EXECUTADA
A14: MUD END FABIANA GONÇALVES PROT:2603.35547 DINHEIRO (JHONATAN) - PAMPULHA | B14: MUD END | D14: VALIDAÇÃO OK ENVIAR AO CADASTRO | E14: 34991006033 | F14: 46115 | G14: =PROPER(TEXT(F14,"DDD")) -> Sex | H14: APOS AS 11:00 | I14: DINHEIRO | J14: ENDEREÇO NOVO: RUA OLIVEIRA LIMA, 959 COMPLEMENTO: CASA UNICA CEP: 38408650 BAIRRO: PAMPULHA | K14: <b>ONT = ONT TP LINK 220 // CONECTOR = VERDE.</b> | L14: =IF(B14="MUD END","NÃO","SIM") -> NÃO | M14: - | N14: SIM | O14: RENNER (ESPOSO DE FABIANA) | P14: 34991301190 | Q14: COMPROVANTE DE ENDEREÇO (CONTRATO DE LOCAÇÃO) EM ANEXO NOME NO COMPROVANTE: FABIANA GONÇALVES (ASSINANTE) | R14: -> FABIO HENRIQUE ALVEZ - SOLICITAÇÃO DE ADESÃO REPROVADA EM 02/02/2022 :. CONSTA NO CADASTRO -> RUA OLIVEIRA LIMA 959 - PAMPULHA (CASA-1) PORÉM NÃO IDENTIFIQUEI DUAS CASA COM O NUMERO 959. (EVIDÊNCIA EM ANEXO) ________________________________________________________________________________ MK NOME -> DERLY RENNER LONDRES CAMPOS (DISSE QUE É ESPOSO DA ASSINANTE): N/C -> FABIANA GONÇALVES (LOCADORA): ASSINANTE DA CONEXÃO -> SEBASTIÃO MANOELDA SILVA (LOCADOR): N/C | S14: =IF(F14<TODAY(),"EXECUTADA",IF(F14=TODAY(),"EM EXECUÇÃO",IF(F14=TODAY()+1,"VALIDAR HOJE",IF(F14>TODAY()+1,"VALIDAR DEPOIS","-")))) -> EXECUTADA
A15: MUD END CLAUDIONOR JOSE SILVA SANTOS PROT:2603.35845 PIX (VAGNER) - JARDIM EUROPA | B15: MUD END | D15: VALIDAÇÃO OK ENVIAR AO CADASTRO | E15: 34988827305 | F15: 46115 | G15: =PROPER(TEXT(F15,"DDD")) -> Sex | H15: APOS AS 13:00 | I15: PIX | J15: ENDEREÇO NOVO: RUA RIO SOLIMÕES, 1331 COMPLEMENTO: CASA UNICA CEP: 38414536 BAIRRO: JARDIM EUROPA | K15: <b>ONT = ONT TP LINK 530 // CONECTOR = VERDE.</b> | L15: =IF(B15="MUD END","NÃO","SIM") -> NÃO | M15: - | N15: SIM | O15: - | P15: - | Q15: COMPROVANTE DE ENDEREÇO (DMAE) EM ANEXO NOME NO COMPROVANTE: DOUGLAS NUNES MATOS (CLAUDIONOR ALEGAR SER O ANTIGO MORADOR) | R15: MK END: N/C MK NOME: DOUGLAS NUNES MATOS (CLAUDIONOR ALEGAR SER O ANTIGO MORADOR) - N/C | S15: =IF(F15<TODAY(),"EXECUTADA",IF(F15=TODAY(),"EM EXECUÇÃO",IF(F15=TODAY()+1,"VALIDAR HOJE",IF(F15>TODAY()+1,"VALIDAR DEPOIS","-")))) -> EXECUTADA
A16: MUD END GILMAR VIANNA SOARES PROT:2603.33901 CARTAO (ANDREZA) - PRESIDENTE ROOSEVELT // | B16: MUD END | D16: VALIDAÇÃO OK ENVIAR AO CADASTRO | E16: 34998971039 | F16: 46115 | G16: =PROPER(TEXT(F16,"DDD")) -> Sex | H16: APÓS AS 13:00 | I16: CARTÃO | J16: ENDEREÇO NOVO: RUA TUFI MAMERI, 305 COMPLEMENTO: CASA ÚNICA CEP: 38401034 BAIRRO: PRESIDENTE ROOSEVELT | K16: <b>ONT = ONT TP LINK 220 // CONECTOR = VERDE.</b> | L16: =IF(B16="MUD END","NÃO","SIM") -> NÃO | M16: - | N16: SIM | O16: - | P16: - | Q16: COMPROVANTE DE ENDEREÇO (CEMIG) EM ANEXO NOME NO COMPROVANTE: ROMILDA SOUZA SANTANA (DISSE QUE É A DONA DO IMÓVEL) | R16: MK END: N/C ________________________________________ MK NOMES: -> ROMILDA SOUZA SANTANA (DISSE QUE É A DONA DO IMÓVEL) - CPF 710.4**.***-**: N/C | S16: =IF(F16<TODAY(),"EXECUTADA",IF(F16=TODAY(),"EM EXECUÇÃO",IF(F16=TODAY()+1,"VALIDAR HOJE",IF(F16>TODAY()+1,"VALIDAR DEPOIS","-")))) -> EXECUTADA
A17: MUD END + ALT PLANO KATIUCIA SILVA SANTOS PROT:2603.32174 ISENTO (HALYSON) - JARDIM EUROPA // *03/04/2026 ÁS 08HS // | B17: MUD END + ALT PLAN | D17: VALIDAÇÃO OK ENVIAR AO CADASTRO PENDENTE ASSINATURA DE CONTRATO | E17: 84999800965 | F17: 46116 | G17: =PROPER(TEXT(F17,"DDD")) -> Sáb | H17: 0.33333333 | I17: ISENTO | J17: ENDEREÇO NOVO: RUA MANCHESTER, 85 COMPLEMENTO: CASA 01 CEP: 38414565 BAIRRO: JARDIM EUROPA | K17: <b>ONT = ONT ZTE // CONECTOR = VERDE.</b> | L17: =IF(B17="MUD END","NÃO","SIM") -> SIM | M17: PLANO ATUAL: 1000 MEGA/99,90 CONTRATADO EM 04/2024 COM FIDELIDADE DE 12 MESES. ROTEADOR: ONT ZTE F 670-L PLANO OFERTADO: 1 GIGA (1.000 MEGA) R$99,90. BENEFÍCIOS: ACESSO GRATUITO AO APP MZTV (CDNTV+) + VOD | N17: SIM | O17: JESSICA (CUNHADA DE KATIUCIA) | P17: 34998616817 | Q17: COMPROVANTE DE ENDEREÇO (CEMIG) EM ANEXO NOME NO COMPROVANTE: ALCINEIA MARQUES GUIMARAES TIBURCIO (DISSE QUE É A PROPRIETARIA DO IMOVÉL) | R17: MK END - SOFIA BARBOSA DE MORAIS: CONEXÃO CANCELADA SEM DÉBITOS - DANIELA PIRES VALADAO: PROCESSO DE ADESÃO CANCELADO (CLIENTE NÃO TEVE INTERESSE EM PAGAR TAXA DE INSTALAÇÃO) - ALCINEIA MARQUES GUIMARAES TIBURCIO (CASA 2): POSSUI CONEXÃO ATIVA COM PROTOCOLO (2603.22437) DE CANCELAMENTO EM ABERTO // FATURA 25/03 NO VALOR DE 79,90 EM ABERTO // MK NOMES - KATIUCIA SILVA SANTOS (ASSINANTE): POSSUI CONEXÃO ATIVA E ADIMPLENTE - ALCINEIA MARQUES GUIMARAES TIBURCIO (CASA 2): POSSUI CONEXÃO ATIVA COM PROTOCOLO (2603.22437) DE CANCELAMENTO EM ABERTO // FATURA 25/03 NO VALOR DE 79,90 EM ABERTO | S17: =IF(F17<TODAY(),"EXECUTADA",IF(F17=TODAY(),"EM EXECUÇÃO",IF(F17=TODAY()+1,"VALIDAR HOJE",IF(F17>TODAY()+1,"VALIDAR DEPOIS","-")))) -> EXECUTADA
A18: MUD END + ALT PLANO LETICIA BARBOSA DOS SANTOS PROT:2603.34539 ISENTO (JOSÉ Jr) - JARAGUÁ // | B18: MUD END + ALT PLAN | D18: VALIDAÇÃO OK ENVIAR AO CADASTRO | E18: 34991737280 | F18: 46116 | G18: =PROPER(TEXT(F18,"DDD")) -> Sáb | H18: 0.33333333 | I18: ISENTO | J18: ENDEREÇO NOVO: RUA ALBERTO TOLEDO BARTON, 70 COMPLEMENTO: CASA UNICA CEP: 38413407 BAIRRO: JARAGUÁ | K18: . <b>ONU = DATA // CONECTOR = VERDE.</b> | L18: =IF(B18="MUD END","NÃO","SIM") -> SIM | M18: PLANO ATUAL: 600 MEGA/79,90 CONTRATADO EM 09/2024 COM FIDELIDADE DE 12 MESES. ROTEADOR: HUAWEI AX2 PLANO OFERTADO: 600 MEGA/79,90. BENEFÍCIOS: ACESSO GRATUITO AO APP MZTV (CDNTV+) | N18: SIM | O18: - | P18: - | Q18: COMPROVANTE DE ENDEREÇO (CEMIG) EM ANEXO NOME NO COMPROVANTE: DOUGLAS CARVALHO DOMINGOS (ESPOSO DA TITULAR) | R18: MK END: IASMYN RODRIGUES CUNHA CPF:705.850.926-30 PROCESSO DE ADESÃO APROVADO NO DIA 12/04/2024 PARA SUA MÃE CRISTIENE SILVA RODRIGUES. CRISTIENE SILVA RODRIGUES CUNHA CPF:912.026.126-87 CONEXÃO CANCELADA POR INADIMPLÊNCIA NO MES 03/2025( DEBITOS R$1706,03) NÃO DEVOLVEU OS EQUIPAMENTOS. MK NOMES: DOUGLAS CARVALHO DOMINGOS CPF 124.7**.***-**(CLIENTE DIZ QUE É SEU ESPOSO)N/C | S18: =IF(F18<TODAY(),"EXECUTADA",IF(F18=TODAY(),"EM EXECUÇÃO",IF(F18=TODAY()+1,"VALIDAR HOJE",IF(F18>TODAY()+1,"VALIDAR DEPOIS","-")))) -> EXECUTADA
A19: MUD END LEANDRO EMANUEL ROSA OLIVEIRA PROT:2603.29238 PIX (BRUNA) - CUSTÓDIO PEREIRA 04/04/2026 ÁS 08HRS // *ANALISE 90 DIAS* | B19: MUD END | D19: ANALISE 90 DIAS TUDO OK .. ENVIAR CADASTRO | E19: 34991194542 | F19: 46116 | G19: =PROPER(TEXT(F19,"DDD")) -> Sáb | H19: 0.33333333 | I19: PIX | J19: ENDEREÇO NOVO: RUA VISCONDE DE OURO PRETO, 115 COMPLEMENTO: CASA FRENTE CEP: 38405202 BAIRRO: CUSTÓDIO PEREIRA | K19: <b>ONT = ONT TP LINK 530 // CONECTOR = VERDE.</b> | L19: =IF(B19="MUD END","NÃO","SIM") -> NÃO | M19: - | N19: NÃO | O19: LUCIANA ROSA DE OLIVIERA (MÃE) | P19: 16981284004 | Q19: COMPROVANTE DE ENDEREÇO (CEMIG) EM ANEXO NOME NO COMPROVANTE: JAMIRO FLORENCIO DOS SANTOS (DIZ SER PROPRIETARIO DO IMOVEL) | R19: MK END: N/C MK NOMES: JAMIRO FLORENCIO DOS SANTOS (PROPRIETARIO): N/C LUCIANA ROSA DE OLIVIERA (MÃE DE LEANDRO): N/C | S19: =IF(F19<TODAY(),"EXECUTADA",IF(F19=TODAY(),"EM EXECUÇÃO",IF(F19=TODAY()+1,"VALIDAR HOJE",IF(F19>TODAY()+1,"VALIDAR DEPOIS","-")))) -> EXECUTADA
A20: MUD END + ALT PLANO ROBSON LIBERIO DA SILVA PROT:2603.34423 ISENTO (HALYSON) - NOSSA SENHORA DAS GRAÇAS // *PEND. COMPROVANTE ENDEREÇO E DE PAGAMENTO* | B20: MUD END + ALT PLAN | D20: VALIDAÇÃO OK ENVIAR AO CADASTRO | E20: 34998824249 | F20: 46116 | G20: =PROPER(TEXT(F20,"DDD")) -> Sáb | H20: 0.41666667 | I20: ISENTO | J20: ENDEREÇO NOVO: RUA CEARÁ, 922 COMPLEMENTO: CASA CEP: 38402018 BAIRRO: NOSSA SENHORA DAS GRAÇAS | K20: <b>ONT = ONT TP LINK 230 // CONECTOR = VERDE.</b> | L20: =IF(B20="MUD END","NÃO","SIM") -> SIM | M20: PLANO ATUAL: 600 MEGA/79,90 CONTRATADO EM 09/2024 COM FIDELIDADE DE 12 MESES. ROTEADOR: ONT TP-LINK XC230 PLANO OFERTADO: 600 MEGA/79,90. BENEFÍCIOS: ACESSO GRATUITO AO APP MZTV (CDNTV+) | N20: SIM | O20: - | P20: - | Q20: COMPROVANTE DE ENDEREÇO (CONTRATO DE LOCAÇÃO) EM ANEXO NOME NO COMPROVANTE: ROBSON LIBERIO DA SILVA (ASSINANTE) | R20: MK NOMES: TATIANE BATISTA MARTINS CORREIA (PROPRIETARIO) - N/C ROBSON LIBERIO DA SILVA (LOCATÁRIO) ASSINANTE, CONEXÃO ATIVA E ADIMPLENTE MK END: N/C | S20: =IF(F20<TODAY(),"EXECUTADA",IF(F20=TODAY(),"EM EXECUÇÃO",IF(F20=TODAY()+1,"VALIDAR HOJE",IF(F20>TODAY()+1,"VALIDAR DEPOIS","-")))) -> EXECUTADA
A21: MUD END VANESSA LISBOA MIRANDA PROT:2603.32068 CARTÃO (LUIS) - CHÁCARAS TUBALINA E QUARTEL **PRÉDIO COM PRUMADA** 04/04/2026 ÁS 10HRS | B21: MUD END | D21: VALIDAÇÃO OK ENVIAR AO CADASTRO | E21: 34991420838 | F21: 46116 | G21: =PROPER(TEXT(F21,"DDD")) -> Sáb | H21: 0.41666667 | I21: cartão | J21: ENDEREÇO NOVO: RUA JOSÉ GARIBALDINO, 350 COMPLEMENTO: TOP LIFE ACAPULCO, BL 18 APT 404 CEP: 38413295 BAIRRO: CHÁCARAS TUBALINA E QUARTEL | K21: <b>ONT = ONT TP LINK 530 // CONECTOR = VERDE.</b> | L21: =IF(B21="MUD END","NÃO","SIM") -> NÃO | M21: - | N21: NÃO | O21: THAUANNY (FILHA DE VANESSA) | P21: (34) 99241-2049 | Q21: COMPROVANTE DE ENDEREÇO (CEMIG) EM ANEXO. NOME NO COMPROVANTE: VITOR FELIPE SOARES FERREIRA (ALEGA SER DONO DA RESIDÊNCIA ) | R21: MK END: N/C MK NOME: - VITOR FELIPE SOARES FERREIRA (ALEGA SER DONO DO IMÓVEL) N/C; - VANESSA LISBOA MIRANDA - CPF: 081.726.936-30- ASSINANTE - CLIENTE ATIVO E ADIMPLENTE COM A EMPRESA | S21: =IF(F21<TODAY(),"EXECUTADA",IF(F21=TODAY(),"EM EXECUÇÃO",IF(F21=TODAY()+1,"VALIDAR HOJE",IF(F21>TODAY()+1,"VALIDAR DEPOIS","-")))) -> EXECUTADA
A22: MUD END + ALT PLANO LUCILIA CANDIDA LIMA SOBRAL PROT:2604.161 ISENTO (ANDREZA) - CHÁCARAS TUBALINA E QUARTEL **PRÉDIO COM PRUMADA** // *TROCA DE EQUIPAMENTO* | B22: MUD END + ALT PLAN | D22: VALIDAÇÃO OK ENVIAR AO CADASTRO COBRAR ASSINATURA DO CONTRATO | E22: 34920008902 | F22: 46116 | G22: =PROPER(TEXT(F22,"DDD")) -> Sáb | H22: APÓS AS 11:00 | I22: ISENTO | J22: ENDEREÇO NOVO: RUA DIMAS MACHADO, 164 COMPLEMENTO: RESIDENCIAL PALLACE PLANALTO - BLOCO 3, APTO 208 CEP: 38413291 BAIRRO: CHÁCARAS TUBALINA E QUARTEL | K22: <b>ONU = DATA // CONECTOR = VERDE.</b> | L22: =IF(B22="MUD END","NÃO","SIM") -> SIM | M22: PLANO ATUAL: 1000 MEGA/99,90 CONTRATADO EM 01/2024 COM FIDELIDADE DE 12 MESES. ROTEADOR: ZTE H199-A PLANO OFERTADO: 1 GIGA (1.000 MEGA) R$99,90. BENEFÍCIOS: ACESSO GRATUITO AO APP MZTV (CDNTV+) + VOD | N22: SIM | O22: - | P22: - | Q22: COMPROVANTE DE ENDEREÇO (TAXA DE MUDANÇA DE CONDOMÍNIO) EM ANEXO NOME NO COMPROVANTE: ALEXIA CRISTINE DE OLIVEIRA MENDONÇA (DISSE QUE É A DONA DO IMÓVEL) | R22: MK END: N/C ________________________________________ MK NOMES: -> ALEXIA CRISTINE DE OLIVEIRA MENDONÇA (DISSE QUE É A DONA DO IMÓVEL) - CPF 101.272.306-29: N/C | S22: =IF(F22<TODAY(),"EXECUTADA",IF(F22=TODAY(),"EM EXECUÇÃO",IF(F22=TODAY()+1,"VALIDAR HOJE",IF(F22>TODAY()+1,"VALIDAR DEPOIS","-")))) -> EXECUTADA
A23: MUD END + ALT PLANO LARA SILVA CIPRIANO (MARIA/MAE) PROT:2603.35997 ISENTO (LUIS) - LOTEAMENTO PORTAL DO VALE II **PRÉDIO COM PRUMADA** // | B23: MUD END + ALT PLAN | D23: PENDENTE CONFERENCIAS | E23: 34999103758 | F23: 46116 | G23: =PROPER(TEXT(F23,"DDD")) -> Sáb | H23: APÓS AS 11:00 | I23: ISENTO | J23: ENDEREÇO NOVO: RUA REINALDO ALVES DA ROCHA, 850 COMPLEMENTO: COND, VISTA DO VALE 02 BL 02 APT 602 CEP: 38436086 BAIRRO: LOTEAMENTO PORTAL DO VALE II | K23: <b>ONT = ONT TP LINK 230 // CONECTOR = VERDE.</b> | L23: =IF(B23="MUD END","NÃO","SIM") -> SIM | M23: PLANO ATUAL: 600 MEGA/79,90 CONTRATADO EM 12/2024 COM FIDELIDADE DE 12 MESES. ROTEADOR: ONT TP-LINK XC230 PLANO OFERTADO: 600 MEGA/79,90. BENEFÍCIOS: ACESSO GRATUITO AO APP MZTV (CDNTV+) | N23: SIM | O23: - | P23: - | Q23: COMPROVANTE DE ENDEREÇO (CONTRATO DE LOCAÇÃO) EM ANEXO NOME NO COMPROVANTE: LARA SILVA CIPRIANO (ASSINANTE) | R23: MK END: N/C MK NOMES: - KEVIN CARVALHO DE CASTRO CPF: 129.955.526-83 - LOCADOR - N/C - LARA SILVA CIPRIANO (MARIA/MAE) - CPF: 884.659.422-34 - LOCATÁRIA (ASSINANTE) CLIENTE ATIVA E ADIMPLENTE COM A EMPRESA. | S23: =IF(F23<TODAY(),"EXECUTADA",IF(F23=TODAY(),"EM EXECUÇÃO",IF(F23=TODAY()+1,"VALIDAR HOJE",IF(F23>TODAY()+1,"VALIDAR DEPOIS","-")))) -> EXECUTADA
A24: MUD END + ALT PLANO EDNEUZA SIQUEIRA LEITE PROT:2604.827 ISENTO (IZABELA) - NOVO MUNDO **PRÉDIO COM PRUMADA** // | B24: MUD END + ALT PLAN | D24: VALIDAÇÃO OK ENVIAR AO CADASTRO PENDENTE ASSINATURA | E24: 34999537343 | F24: 46116 | G24: =PROPER(TEXT(F24,"DDD")) -> Sáb | H24: 0.33333333 | I24: ISENTO | J24: ENDEREÇO NOVO: RUA SANTINA ZANATTA, 103 COMPLEMENTO: AP 307 CEP: 38409047 BAIRRO: NOVO MUNDO | K24: <b>ONT = ONT TP LINK 230 // CONECTOR = VERDE.</b> | L24: =IF(B24="MUD END","NÃO","SIM") -> SIM | M24: PLANO ATUAL: 600 MEGA/79,90 CONTRATADO EM 06/2025 COM FIDELIDADE DE 12 MESES. ROTEADOR: ONT TP-LINK XC230 PLANO OFERTADO: 600 MEGA/79,90. BENEFÍCIOS: ACESSO GRATUITO AO APP MZTV (CDNTV+) | N24: SIM | O24: IRINEU (FILHO DE EDNEUZA) | P24: 19981470830 | Q24: COMPROVANTE DE ENDEREÇO (CONTRATO DE COMPRA E VENDA) EM ANEXO NOME NO COMPROVANTE: IRINEU SIQUEIRA LEITE (FILHO DE EDNEUZA) | R24: MK END - N/C MK NOMES: VINICIUS CARNEIRO DIAS (VENDEDOR) - N/C IRINEU SIQUEIRA LEITE (COMPRADOR / FILHO DA TITULAR) - N/C ____________________________________________________________ REPRESENTANTES ITAÚ UNIBANCO S.A: ANDRE BERANGER VIEIRA (297.484.678-56) - N/C CIRLENE ALVES DOS SANTOS (360.348.728-12) - N/C KELLY CRISTINA KRAUT DE ALMEIDA (260.214.648-00) - N/C LAIS SANTANA GONCALVES DA SILVA (421.336.208-69) - N/C MARIA ELISA MORI (092.650.258-16) - N/C NATALIA DA COSTA ARAUJO (444.426.928-66) - N/C RANULFO DA ROCHA SILVA (222.833.068-09) - N/C RAPHAEL GERMANO AMARO DA SILVA (399.010.958-83) - N/C VANESSA MODESTO DE ABREU (383.100.548-66) - N/C WESLLEY DA SILVA RAMOS DO NASCIMENTO (344.258.558-92) - N/C ANDERSON HENRIQUE TEIXEIRA NOGUEIRA (NÃO HÁ ESPECIFICAÇÃO DA OCUPAÇÃO DO MESMO) - N/C BARBARA APARECIDA OTONI (NÃO HÁ ESPECIFICAÇÃO DA OCUPAÇÃO DA MESMA) - N/C | S24: =IF(F24<TODAY(),"EXECUTADA",IF(F24=TODAY(),"EM EXECUÇÃO",IF(F24=TODAY()+1,"VALIDAR HOJE",IF(F24>TODAY()+1,"VALIDAR DEPOIS","-")))) -> EXECUTADA
A25: MUD END KLEVERSON ERRERA DE SOUZA PROT:2604.1722 PIX (ANDREZA) - SANTA MÔNICA | B25: MUD END + ALT PLAN | D25: VALIDAÇÃO OK ENVIAR AO CADASTRO | E25: 17997351940 | F25: 46116 | G25: =PROPER(TEXT(F25,"DDD")) -> Sáb | H25: APÓS AS 11:00 HORAS | I25: PIX | J25: ENDEREÇO NOVO: AVENIDA ORTÍZIO BORGES, 1398 COMPLEMENTO: CASA FUNDO CEP: 38408263 BAIRRO: SANTA MÔNICA | K25: <b>ONT = ONT ZTE // CONECTOR = VERDE.</b> | L25: =IF(B25="MUD END","NÃO","SIM") -> SIM | M25: PLANO ATUAL: 600 MEGA/79,90 CONTRATADO EM 04/2025 COM FIDELIDADE DE 12 MESES. ROTEADOR: ONT ZTE F 670-L PLANO OFERTADO: 600 MEGA/79,90. BENEFÍCIOS: ACESSO GRATUITO AO APP MZTV (CDNTV+) | N25: SIM | O25: - | P25: - | Q25: COMPROVANTE DE ENDEREÇO (CONTRATO DE LOCAÇÃO) EM ANEXO NOME NO COMPROVANTE: KLEVERSON ERRERA DE SOUZA (ASSINANTE) | R25: MK END: N/C ________________________________________ MK NOMES: -> ANTONIO PEREIRA TOSTA (LOCADOR) - CPF 103.551.891-00: N/C -> KLEVERSON ERRERA DE SOUZA (LOCATÁRIO) - CPF 102.820.168-05: ASSINANTE DA CONEXÃO. -> SANDRA ELISA CASALE (ESPOSA DO LOCATÁRIO) - CPF 102.852.798-58: N/C | S25: =IF(F25<TODAY(),"EXECUTADA",IF(F25=TODAY(),"EM EXECUÇÃO",IF(F25=TODAY()+1,"VALIDAR HOJE",IF(F25>TODAY()+1,"VALIDAR DEPOIS","-")))) -> EXECUTADA
A26: MUD END WESLEY DE SOUZA GONCALVES PROT:2603.32228 PIX (VAGNER) - SÃO JORGE // *ANALISE* | B26: MUD END | D26: -PENDENTE COMPROVANTE - ENDEREÇO NÃO ALTERADO - MENSALIDADE PENDENTE - ANÁLISE 90 DIAS | E26: 34997153668 | F26: 46116 | G26: =PROPER(TEXT(F26,"DDD")) -> Sáb | H26: APÓS AS 11:00 | I26: PIX | J26: ENDEREÇO NOVO: AVENIDA SERRA DO ESPINHAÇO, 775 COMPLEMENTO: CASA UNICA CEP: 38410384 BAIRRO: SÃO JORGE | K26: <b>ONU = DATA // CONECTOR = VERDE.</b> | L26: =IF(B26="MUD END","NÃO","SIM") -> NÃO | M26: - | N26: SIM | O26: - | P26: - | Q26: PENDENTE COMPROVANTE | S26: =IF(F26<TODAY(),"EXECUTADA",IF(F26=TODAY(),"EM EXECUÇÃO",IF(F26=TODAY()+1,"VALIDAR HOJE",IF(F26>TODAY()+1,"VALIDAR DEPOIS","-")))) -> EXECUTADA
A27: RESERVA RONALD / MUD END / JUVENIL MARIO BENEDITO | B27: MUD END + ALT PLAN | D27: -Pendente comprovante atualizado - Complemento, melhorar informação. descrito como "casa ao lado" - Contrato nao assinado | E27: 34992807809 | F27: 46116 | G27: =PROPER(TEXT(F27,"DDD")) -> Sáb | H27: Após as 11:00 horas | I27: ISENTO | J27: ENDEREÇO NOVO: RUA NATALINA DE CASTRO PEREIRA, 15 COMPLEMENTO: CASA AO LADO CEP: 38401116 BAIRRO: PRESIDENTE ROOSEVELT | K27: <b>ONT = ONT TP LINK 220 // CONECTOR = VERDE.</b> | L27: =IF(B27="MUD END","NÃO","SIM") -> SIM | M27: PLANO ATUAL: 150 MEGA/59,90 CONTRATADO EM 06/2025 COM FIDELIDADE DE 12 MESES. ROTEADOR: ONT TP-LINK XC220 PLANO OFERTADO: 150 MEGA/59,90. BENEFÍCIOS: ACESSO GRATUITO AO APP MZTV (CDNTV+) | N27: SIM | O27: - | P27: - | Q27: PENDENTE COMPROVANTE | S27: =IF(F27<TODAY(),"EXECUTADA",IF(F27=TODAY(),"EM EXECUÇÃO",IF(F27=TODAY()+1,"VALIDAR HOJE",IF(F27>TODAY()+1,"VALIDAR DEPOIS","-")))) -> EXECUTADA
A28: MUD END NAIANE RODRIGUES DE SOUSA MELO PROT:2603.34560 PIX (BRUNA) - SEGISMUNDO PEREIRA // | B28: MUD END | D28: VALIDAÇÃO OK ENVIAR AO CADASTRO | E28: 34997684409 | F28: 46118 | G28: =PROPER(TEXT(F28,"DDD")) -> Seg | H28: 0.625 | I28: PIX | J28: ENDEREÇO NOVO: RUA JOÃO ÂNGELO SCHIAVINATO, 1613 COMPLEMENTO: CASA ÚNICA CEP: 38408272 BAIRRO: SEGISMUNDO PEREIRA | K28: <b>ONT = ONT TP LINK 530 // CONECTOR = VERDE.</b> | L28: =IF(B28="MUD END","NÃO","SIM") -> NÃO | M28: - | N28: NÃO | O28: CLAITON DE OLIVEIRA MELO (ESPOSO) | P28: 34 9128-6717 | Q28: COMPROVANTE DE ENDEREÇO (CONTRATO DE LOCAÇÃO) EM ANEXO NOME NO COMPROVANTE: NAIANE RODRIGUES DE SOUSA MELO (ASSINANTE) | R28: MK END: N/C MK NOMES: VANDA LEONARDO ALVES FREITAS (LOCADORA):N/C NAIANE RODRIGUES DE SOUSA MELO (LOCATÁRIA/ASSINANTE): CONEXÃO ATIVA E SEM PENDENCIAS. CLAITON DE OLIVEIRA MELO (LOCATÁRIO/ESPOSO DE NAIANE):N/C CREUZA MARIA DE OLIVEIRA MELO (FIADORA):N/C CEMIG (CONCESSIONÁRIA):N/C BANCO BRADESCO (INSTITUIÇÃO FINANCEIRA):N/C | S28: =IF(F28<TODAY(),"EXECUTADA",IF(F28=TODAY(),"EM EXECUÇÃO",IF(F28=TODAY()+1,"VALIDAR HOJE",IF(F28>TODAY()+1,"VALIDAR DEPOIS","-")))) -> EXECUTADA
A29: MUD END PIETRO URBANO GALVAO PROT:2603.35889 PIX (JHONATAN) - **PRÉDIO SEM PRUMADA - ENVIAR TÉCNICO DUPLADO** *AGUARDANDO ANALISE PRÉDIO (VERTICAL)* | B29: MUD END | D29: VALIDAÇÃO OK ENVIAR AO CADASTRO | E29: 34999529448 | F29: 46118 | G29: =PROPER(TEXT(F29,"DDD")) -> Seg | H29: 0.54166667 | I29: PIX | J29: ENDEREÇO NOVO: RUA TUPACIGUARA, 400 COMPLEMENTO: AP 401 CEP: 38400618 BAIRRO: NOSSA SENHORA APARECIDA | K29: <b>ONT = ONT TP LINK 530 // CONECTOR = VERDE.</b> | L29: =IF(B29="MUD END","NÃO","SIM") -> NÃO | M29: - | N29: SIM | O29: - | P29: - | Q29: COMPROVANTE DE ENDEREÇO (DMAE) EM ANEXO NOME NO COMPROVANTE: PIETRO URBANO GALVÃO (ASSINANTE) | R29: MK END N/C MK NOMES -> PIETRO URBANO GALVÃO (LOCATÁRIO / ASSINANTE DA CONEXÃO) -> VALDEMAR DA SILVA ZUZA (LOCADOR / PROPRIETÁRIO DO IMÓVEL): N/C -> MÁRCIO ANDRÉ GUIMARÃES GALVÃO (FIADOR): POSSUI CONEXÃO ATIVA E ADIMPLENTE -> TIZIANA ADRIANA URBANO (CÔNJUGE DO FIADOR / FIADORA): N/C -> OBJETIVA IMÓVEIS S/S LTDA (IMOBILIÁRIA): N/C | S29: =IF(F29<TODAY(),"EXECUTADA",IF(F29=TODAY(),"EM EXECUÇÃO",IF(F29=TODAY()+1,"VALIDAR HOJE",IF(F29>TODAY()+1,"VALIDAR DEPOIS","-")))) -> EXECUTADA
A30: MUD END ERIKA CRISTINA ALESSI (ATELIE DE ALTA COSTURA) PROT:2604.1333 PIX (VICTOR H.) - OSVALDO REZENDE // PENDENTE COMPROVANTE DE ENDEREÇO | B30: MUD END | D30: PENDENTE COMPROVANTE | E30: 34991195973 | F30: 46118 | G30: =PROPER(TEXT(F30,"DDD")) -> Seg | I30: PIX | J30: ENDEREÇO NOVO: RUA FRANCISCO SALES, 1140 COMPLEMENTO: COMERCIO CEP: 38400440 BAIRRO: OSVALDO REZENDE | K30: <b>ONT = ONT ZTE // CONECTOR = VERDE.</b> | L30: =IF(B30="MUD END","NÃO","SIM") -> NÃO | M30: - | N30: SIM | O30: - | P30: - | Q30: COMPROVANTE DE ENDEREÇO (DMAE) EM ANEXO NOME NO COMPROVANTE: SONIA MARIA BORBA (DISSE SER IRMÃ DO PROPRIETÁRIO DO IMÓVEL) | R30: MK END: N/C MK NOMES: SONIA MARIA BORBA (DISSE SER IRMÃ DO PROPRIETÁRIO DO IMÓVEL) N/C | S30: =IF(F30<TODAY(),"EXECUTADA",IF(F30=TODAY(),"EM EXECUÇÃO",IF(F30=TODAY()+1,"VALIDAR HOJE",IF(F30>TODAY()+1,"VALIDAR DEPOIS","-")))) -> EXECUTADA
A31: mud end IRIS DE FATIMA MARCELINO CAMARA prot (Victor) | B31: MUD END | D31: VALIDAÇÃO OK ENVIAR AO CADASTRO | E31: 34999811485 | F31: 46118 | G31: =PROPER(TEXT(F31,"DDD")) -> Seg | H31: 0.41666667 | I31: ISENTO | J31: ENDEREÇO NOVO: RUA NICARÁGUA, 794 COMPLEMENTO: APTO 102 CEP: 38405100 BAIRRO: TIBERY | K31: <b>ONT = ONT TP LINK 230 // CONECTOR = VERDE.</b> | L31: =IF(B31="MUD END","NÃO","SIM") -> NÃO | M31: PLANO ATUAL: 1000 MEGA/99,90 CONTRATADO EM 05/2024 COM FIDELIDADE DE 12 MESES. ROTEADOR: ONT TP-LINK XC230 PLANO OFERTADO: 1 GIGA (1.000 MEGA) R$99,90. BENEFÍCIOS: ACESSO GRATUITO AO APP MZTV (CDNTV+) + VOD | N31: SIM | O31: - | P31: - | Q31: COMPROVANTE DE ENDEREÇO (CONTRATO DE LOCAÇÃO) EM ANEXO NOME NO COMPROVANTE: IRIS DE FATIMA MARCELINO CAMARA (ASSINANTE) | R31: MK NOMES: ELCI LOURENÇO BORGES CPF 456.253.446-04 (LOCADOR) N/C MATILDE ALVES BORGES CPF 260.176.956-49 (LOCADORA) N/C IRIS DE FÁTIMA MARCELINO CAMARA RG 143.693.111-87 (LOCATÁRIA) ASSINANTE, CONTRATOU EM 05/2024 CONEXÃO ATIVA E ADIMPLENTE CARLA MARCELINO CÂMARA RG 054.957.476-67 (TESTEMUNHA) N/C MK END: N/C | S31: =IF(F31<TODAY(),"EXECUTADA",IF(F31=TODAY(),"EM EXECUÇÃO",IF(F31=TODAY()+1,"VALIDAR HOJE",IF(F31>TODAY()+1,"VALIDAR DEPOIS","-")))) -> EXECUTADA
A32: MUD END + ALT PLANO LUCAS FERREIRA GOMES PROT:2603.34716 ISENTO (JHONATAN) - DANIEL FONSECA | | B32: MUD END + ALT PLAN | D32: JA VALIDADO ANTERIORMENTE | E32: 34991631067 | F32: 46118 | G32: =PROPER(TEXT(F32,"DDD")) -> Seg | H32: 0.54166667 | I32: ISENTO | J32: ENDEREÇO NOVO: RUA VARGINHA, 1155 COMPLEMENTO: COND. MARANATA, APT 203 CEP: 38400322 BAIRRO: DANIEL FONSECA | K32: . <b>ONT = ONT ZTE // CONECTOR = VERDE.</b> | L32: =IF(B32="MUD END","NÃO","SIM") -> SIM | M32: PLANO ATUAL: 1000 MEGA/99,90 CONTRATADO EM 07/2025 COM FIDELIDADE DE 12 MESES. ROTEADOR: ONT ZTE F 670-L PLANO SOLICITADO: 1 GIGA (1.000 MEGA) R$99,90. BENEFÍCIOS: ACESSO GRATUITO AO APP MZTV (CDNTV+) + VOD | N32: NÃO | O32: DOUGLAS FERNANDES BORGES. (INQUILINO) | P32: 64 9328-2617 | Q32: COMPROVANTE DE ENDEREÇO (CONTRATO DE LOCAÇÃO) EM ANEXO NOME NO COMPROVANTE: DOUGLAS FERNANDES BORGES (INQUILINO) | R32: MK END: N/C ___________________________ MK NOMES: -> SOCRATES RODRIGUES QUEIROZ - CPF: 052.678.796-14 - LOCADOR DO IMÓVEL - CLIENTE ATIVO NO ENDEREÇO: RUA SEBASTIAO DE FREITAS, 287. ADIMPLENTE COM EMPRESA; -> POLIANA EVANGELISTA SILVA - CPF: 059.825.136-79 - LOCATÁRIA DO IMÓVEL - N/C ; -> DOUGLAS FERNANDES BORGES - CPF: 056.809.281-26 - LOCATÁRIO DO IMÓVEL - N/C ; -> LUCAS FERREIRA GOMES - CPF: 065.584.586-08 - CLIENTE ATIVO E ADIMPLENTE COM A EMPRESA. | S32: =IF(F32<TODAY(),"EXECUTADA",IF(F32=TODAY(),"EM EXECUÇÃO",IF(F32=TODAY()+1,"VALIDAR HOJE",IF(F32>TODAY()+1,"VALIDAR DEPOIS","-")))) -> EXECUTADA
A33: MUD END BRENO SANTOS RESENDE PROT:2604.853 PIX (JOSÉ Jr) - PRESIDENTE ROOSEVELT *PENDENTE COMPROVANTE* | B33: MUD END | D33: VALIDAÇÃO OK ENVIAR AO CADASTRO | E33: 34993110530 | F33: 46118 | G33: =PROPER(TEXT(F33,"DDD")) -> Seg | H33: 0.70833333 | I33: PIX | J33: ENDEREÇO NOVO: RUA FERNANDO ALVES VIEIRA, 12 COMPLEMENTO: CASA UNICA CEP: 38401232 BAIRRO: PRESIDENTE ROOSEVELT | K33: <b>ONT = ONT TP LINK 530 // CONECTOR = VERDE.</b> | L33: =IF(B33="MUD END","NÃO","SIM") -> NÃO | M33: - | N33: SIM | O33: - | P33: - | Q33: COMPROVANTE DE ENDEREÇO (CEMIG) EM ANEXO NOME NO COMPROVANTE: DANIEL SOUZA RESENDE (CLIENTE DIZ QUE É O MORADOR ANTIGO) | R33: MK END:N/C NK NOMES: DANIEL SOUZA RESENDE CPF:806.1**.***-**(CLIENTE DIZ QUE É O MORADOR ANTIGO)N/C | S33: =IF(F33<TODAY(),"EXECUTADA",IF(F33=TODAY(),"EM EXECUÇÃO",IF(F33=TODAY()+1,"VALIDAR HOJE",IF(F33>TODAY()+1,"VALIDAR DEPOIS","-")))) -> EXECUTADA
A34: MUD END + ALT PLANO JULIANA GONCALVES BEIJO PROT:2603.33541 ISENTO (VAGNER) - PORTAL DO VALE **PRÉDIO COM PRUMADA** | B34: MUD END + ALT PLAN | D34: VALIDAÇÃO OK ENVIAR AO CADASTRO COBRAR ASSINATURA DO CONTRATO | E34: 34988720868 | F34: 46118 | G34: =PROPER(TEXT(F34,"DDD")) -> Seg | H34: 0.70833333 | I34: ISENTO | J34: ENDEREÇO NOVO: RUA REINALDO ALVES DA ROCHA, 867 COMPLEMENTO: BLOCO 2 AP 1008 CEP: 38436086 BAIRRO: LOTEAMENTO PORTAL DO VALE II | K34: <b>ONT = ONT TP LINK 220 // CONECTOR = VERDE.</b> | L34: =IF(B34="MUD END","NÃO","SIM") -> SIM | M34: PLANO ATUAL: 150 MEGA/59,90 CONTRATADO EM 09/2024 COM FIDELIDADE DE 12 MESES. ROTEADOR: ONT TP-LINK XC220 PLANO OFERTADO: 150 MEGA/59,90. BENEFÍCIOS: ACESSO GRATUITO AO APP MZTV (CDNTV+) | N34: SIM | O34: - | P34: - | Q34: COMPROVANTE DE ENDEREÇO (DMAE) EM ANEXO NOME NO COMPROVANTE: DANIELA DE OLIVEIRA FARINA (DISSE SER ANTIGA PROPRIETÁRIA) | R34: MK END: HUDSON MARQUETE BEIJO (JULIANA DISSE SER SEU CÔNJUGE) – POSSUI UM PEDIDO DE INSTALAÇÃO REALIZADO NO DIA 19/03/2026. AO QUESTIONAR, INFORMOU QUE HUDSON RESIDE COM ELA NO LOCAL E QUE O PEDIDO FOI FEITO ANTES DA DECISÃO ENTRE CONTRATAR UM NOVO PLANO OU SOLICITAR A MUDANÇA. RELATOU AINDA QUE HUDSON IRÁ SOLICITAR O CANCELAMENTO DO PEDIDO DE INSTALAÇÃO. MK NOME: DANIELA DE OLIVEIRA FARINA (DISSE SER ANTIGA PROPRIETÁRIA)- N/C MARCIO ANTONIO DE FREITAS JUNIOR (DISSE SER ANTIGO MORADOR) - N/C | S34: =IF(F34<TODAY(),"EXECUTADA",IF(F34=TODAY(),"EM EXECUÇÃO",IF(F34=TODAY()+1,"VALIDAR HOJE",IF(F34>TODAY()+1,"VALIDAR DEPOIS","-")))) -> EXECUTADA
A35: MUD END + ALT PLANO JULIANA COUTINHO FERREIRA PROT:2603.18313 ISENTO (VICTOR H.) - TOCANTINS // | B35: MUD END + ALT PLAN | C35: mensalidade pendente demais conferencias ok. | E35: 34998613955 | F35: 46118 | G35: =PROPER(TEXT(F35,"DDD")) -> Seg | H35: 0.625 | I35: ISENTO | J35: ENDEREÇO NOVO: RUA APARECIDA DE FÁTIMA CUNHA, 190 COMPLEMENTO: CASA FUNDO CEP: 38415345 BAIRRO: TOCANTINS | K35: <b>ONT = ONT TP LINK 220 // CONECTOR = VERDE.</b> | L35: =IF(B35="MUD END","NÃO","SIM") -> SIM | M35: PLANO ATUAL: 150 MEGA/59,90 CONTRATADO EM 04/2025 COM FIDELIDADE DE 12 MESES. ROTEADOR: ONT TP-LINK XC220 PLANO OFERTADO: 150 MEGA/59,90. BENEFÍCIOS: ACESSO GRATUITO AO APP MZTV (CDNTV+) | N35: SIM | O35: - | P35: - | Q35: COMPROVANTE DE ENDEREÇO (CEMIG) EM ANEXO NOME NO COMPROVANTE: JULIANA COUTINHO FERREIRA (ASSINANTE) | R35: MK END: - ANA VITORIA PEREIRA CAMPOS - CPF: 043.955.962-66 - FICHA CADASTRAL REALIZADA EM 11/2022 NA QUAL FOI REPROVADA; - WANISLAYLA FERNANDA DA COSTA - CPF: 112.169.146-30 - CONEXÃO ATIVA NO MESMO ENDEREÇO ENTRETANTO COMPLEMENTO É CASA FRENTE. CLIENTE ATIVA E ADIMPLENTE COM A EMPRESA. MK NOMES: - JULIANA COUTINHO FERREIRA - CPF: 705.333.442-20 - ASSINANTE - CLIENTE ATIVA E ADIMPLENTE COM A EMPRESA. | S35: =IF(F35<TODAY(),"EXECUTADA",IF(F35=TODAY(),"EM EXECUÇÃO",IF(F35=TODAY()+1,"VALIDAR HOJE",IF(F35>TODAY()+1,"VALIDAR DEPOIS","-")))) -> EXECUTADA
A36: MUD END + ALT PLANO KENIA CRISTINA AQUINO CARVALHO PROT:2603.34621 ISENTO (HALYSON) - PRESIDENTE ROOSEVELT // *PEND. COMPROVANTE ENDEREÇO* | B36: MUD END + ALT PLAN | D36: PENDENTE COMPROVANTE SEM OS GERADA | E36: 34998954165 | F36: 46118 | G36: =PROPER(TEXT(F36,"DDD")) -> Seg | H36: 0.41666667 | I36: ISENTO | J36: ENDEREÇO NOVO: AVENIDA ADRIANO BAILONI, 64 COMPLEMENTO: SOBRADO CEP: 38401092 BAIRRO: PRESIDENTE ROOSEVELT | L36: =IF(B36="MUD END","NÃO","SIM") -> SIM | M36: PLANO ATUAL: 1000 MEGA/99,90 CONTRATADO EM 02/2025 COM FIDELIDADE DE 12 MESES. ROTEADOR: ONT TP-LINK X530 PLANO OFERTADO: 1 GIGA (1.000 MEGA) R$99,90. BENEFÍCIOS: ACESSO GRATUITO AO APP MZTV (CDNTV+) + VOD | Q36: PENDENTE COMPROVANTE | S36: =IF(F36<TODAY(),"EXECUTADA",IF(F36=TODAY(),"EM EXECUÇÃO",IF(F36=TODAY()+1,"VALIDAR HOJE",IF(F36>TODAY()+1,"VALIDAR DEPOIS","-")))) -> EXECUTADA
A37: MUD END ELEUBER DOS SANTOS PROT:2604.302 DINHEIRO (BRUNA) - JARDIM PATRÍCIA // *PEND COMPROVANTE DE END* *PEND VALIDAÇÃO DO TITULAR* | B37: MUD END | D37: PENDENTE COMPROVANTE | E37: 34996862353 | F37: 46118 | G37: =PROPER(TEXT(F37,"DDD")) -> Seg | I37: DINHEIRO | J37: ENDEREÇO NOVO: RUA ARDÓSIA, 52 COMPLEMENTO: CASA FRENTE CEP: 38414136 BAIRRO: JARDIM PATRÍCIA | K37: <b>ONT = ONT TP LINK 220 // CONECTOR = VERDE.</b> | L37: =IF(B37="MUD END","NÃO","SIM") -> NÃO | M37: - | N37: SIM | O37: EVA (ESPOSA DE ELEUBER) | P37: 3498407-2244 | S37: =IF(F37<TODAY(),"EXECUTADA",IF(F37=TODAY(),"EM EXECUÇÃO",IF(F37=TODAY()+1,"VALIDAR HOJE",IF(F37>TODAY()+1,"VALIDAR DEPOIS","-")))) -> EXECUTADA
A38: MUD END + ALT PLANO KEVIN XAVIER RIBEIRO PROT:2603.34547 ISENTO (LUIS) - SEGISMUNDO PEREIRA **PRÉDIO COM PRUMADA** // | B38: MUD END + ALT PLAN | D38: PENDENTE APENAS CONFERENCIAS | E38: 34992870010 | F38: 46118 | G38: =PROPER(TEXT(F38,"DDD")) -> Seg | H38: 0.41666667 | I38: ISENTO | J38: ENDEREÇO NOVO: RUA JOÃO BALBINO, 1833 COMPLEMENTO: CONDOMINIO METROPOLI 2 BL D APT 203 CEP: 38408265 BAIRRO: SEGISMUNDO PEREIRA | K38: . <b>ONT = ONT ZTE // CONECTOR = VERDE.</b> | L38: =IF(B38="MUD END","NÃO","SIM") -> SIM | M38: PLANO ATUAL: 500 MEGA/79,90 CONTRATADO EM 04/2024 COM FIDELIDADE DE 12 MESES. ROTEADOR: ONT ZTE F 670-L PLANO OFERTADO: 600 MEGA/79,90. BENEFÍCIOS: ACESSO GRATUITO AO APP MZTV (CDNTV+) | N38: SIM | O38: - | P38: - | Q38: COMPROVANTE DE ENDEREÇO (CONTRATO DE LOCAÇÃO) EM ANEXO NOME NO COMPROVANTE: FLÁVIA LAYLA ALVES AMERICANO (KEVIN ALEGA SER SUA ESPOSA) | R38: MK END: POSSUI UMA FICHA CADASTRAL REALIZADA NO DIA 30/03/2026 NO NOME DE FLAVIA LAYLA ALVES AMERICANO (KEVIN ALEGA SER SUA ESPOSA). MK NOMES: - ANA PAULA PEREIRA DA SILVA – CPF: 866.464.196-04 – LOCADORA - CONEXÃO CANCELADA EM 11/2023 NO ENDEREÇO RUA ALABASTRO, 166. EQUIPAMENTOS FORAM DEVOLVIDOS E SEM DÉBITO EM ABERTO. - SILONE FERREIRA DA SILVA – CPF: 772.001.101-59 – LOCADORA - N/C - FLÁVIA LAYLA ALVES AMERICANO – CPF: 082.496.186-29 – LOCATÁRIA - FOI REALIZADO A FICHA CADASTRAL NA DATA 30/03/2026 PARA O MESMO ENDEREÇO QUE KEVIN ESTÁ SE MUDANDO: RUA JOAO BALBINO, 1833 - BL.D, APT.203 - KEVIN XAVIER RIBEIRO - CPF: 121.764.336-29 - TESTEMUNHA (ASSINANTE) - CLIENTE ATIVO E ADIMPLENTE COM A EMPRESA. | S38: =IF(F38<TODAY(),"EXECUTADA",IF(F38=TODAY(),"EM EXECUÇÃO",IF(F38=TODAY()+1,"VALIDAR HOJE",IF(F38>TODAY()+1,"VALIDAR DEPOIS","-")))) -> EXECUTADA
A39: MUD END CARLOS HAILTON MUNIZ FERREIRA PROT:2603.34987 DINHEIRO (RONALD) - MORUMBI | B39: MUD END | D39: ENDEREÇO NAO ALTERADO NA OS CORRIGIR PROTOCOLO + OS: MUDANÇA AGENDADA PARA DIA 07/04/2026 ÀS 10:00 HRS. COBRAR COMPROVANTE PAGAMENTO REAGENDADO | E39: 34996941853 | F39: 46119 | G39: =PROPER(TEXT(F39,"DDD")) -> Ter | H39: 0.33333333 | I39: DINHEIRO | J39: ENDEREÇO NOVO: RUA ARRUDA, 203 COMPLEMENTO: CASA ÚNICA CEP: 38407129 BAIRRO: MORUMBI | K39: <b>ONU = DATA // CONECTOR = VERDE.</b> | L39: =IF(B39="MUD END","NÃO","SIM") -> NÃO | M39: - | N39: SIM | O39: - | P39: - | Q39: COMPROVANTE DE ENDEREÇO (CEMIG) EM ANEXO NOME NO COMPROVANTE: MARIA APARECIDA DA SILVA (ANTIGA INQUILINA) | R39: MK END; JHOATAN JUNIO RODRIGUES LIMA SOLICITOU CONTRATAÇÃO EM 04/2025 PORÉM NÃO FOI APROVADO COM INSTALAÇÃO GRATUITA, PORÉM NÃO TEVE INTERESSE. MK NOME; CARLOS HAILTON MUNIZ FERREIRA (ASSINANTE) CONEXÃO ATIVA E CLIENTE ADIMPLENTE MARIA APARECIDA DA SILVA 366.4**.***-** (ANTIGA INQUILINA) N/C | S39: =IF(F39<TODAY(),"EXECUTADA",IF(F39=TODAY(),"EM EXECUÇÃO",IF(F39=TODAY()+1,"VALIDAR HOJE",IF(F39>TODAY()+1,"VALIDAR DEPOIS","-")))) -> EXECUTADA
A40: MUD END IVALDA PEREIRA DA SILVA PROT: 2603.35714 DINHEIRO (HALYSON) - TIBERY | B40: MUD END | D40: VALIDAÇÃO OK ENVIAR AO CADASTRO | E40: 34999773460 | F40: 46119 | G40: =PROPER(TEXT(F40,"DDD")) -> Ter | H40: 0.33333333 | I40: DINHEIRO | J40: ENDEREÇO NOVO: RUA GRÉCIA, 429 COMPLEMENTO: CASA 3 CEP: 38405064 BAIRRO: TIBERY | K40: <b>ONT = ONT TP LINK 220 // CONECTOR = VERDE.</b> | L40: =IF(B40="MUD END","NÃO","SIM") -> NÃO | M40: - | N40: SIM | O40: SIDNEY (ESPOSO DE IVALDA) | P40: 34996945543 | Q40: COMPROVANTE DE ENDEREÇO (DMAE) EM ANEXO NOME NO COMPROVANTE: VAIDE VENANCIO DA SILVA (PAI DA ASSINANTE) | R40: MK END: N/C MK NOMES - VAIDE VENANCIO DA SILVA (PROPRIETÁRIO E PAI DA ASSINANTE): N/C - IVALDA PEREIRA DA SILVA (ASSINANTE): POSSUI CONEXÃO ATIVA E ADIMPLENTE. - SIDNEI ROBERTO GOULART DOS SANTOS (ESPOSO DA ASSINANTE): PEDIDO DE ADESÃO APROVADO PARA ESPOSA *IVALDA PEREIRA DA SILVA 16/05/2025 | S40: =IF(F40<TODAY(),"EXECUTADA",IF(F40=TODAY(),"EM EXECUÇÃO",IF(F40=TODAY()+1,"VALIDAR HOJE",IF(F40>TODAY()+1,"VALIDAR DEPOIS","-")))) -> EXECUTADA
A41: MUD END + ALT PLANO CASA TELAS E CIA LTDA (LOJA 2) PROT:2604.2152 ISENTO (RONALD) - PLANALTO | B41: MUD END + ALT PLAN | D41: COMPLEMENTO EM PROTOCOLO E OS NÃO CONFEREM NAO CONSTA COMENTÁRIO SOBRE COMPROVANTE DE RESIDENCIA | E41: 34996700174 | F41: 46119 | G41: =PROPER(TEXT(F41,"DDD")) -> Ter | H41: 0.41666667 | I41: ISENTO | J41: ENDEREÇO NOVO: RUA ANTÔNIO VICENTE FERREIRA, 618 COMPLEMENTO: LOJA CEP: 38413213 BAIRRO: PLANALTO | K41: <b>ONT = ONT TP LINK 530 // CONECTOR = VERDE.</b> | L41: =IF(B41="MUD END","NÃO","SIM") -> SIM | M41: PLANO ATUAL: 1 GIGA (1.000 MEGA) R$120,00 + IP PUBLICO DINAMICO CONTRATADO EM 03/2025 COM FIDELIDADE DE 12 MESES. ROTEADOR: ONT TP-LINK X530 PLANO OFERTADO: 1 GIGA (1.000 MEGA) R$120,00 + IP PUBLICO DINAMICO. BENEFÍCIOS: ACESSO GRATUITO AO APP MZTV (CDNTV+) + VOD | N41: NÃO | O41: HEITOR (GERENTE DA CASA TELAS E CIA LTDA ) | P41: 34996700174 | Q41: COMPROVANTE DE ENDEREÇO (CEMIG) EM ANEXO NOME NO COMPROVANTE: GILCIMAR OLIVEIRA MENDONÇA (LOCADOR/PROPRIETARIO) | R41: MK END; CASA TELAS E CIA LTDA SOLICITOU O CANCELAMENTO EM 11/2025, DEVOLVEU OS EQUIPAMENTOS E REALIZOU PAGAMENTO DOS DÉBITOS. EM LIGAÇÃO MARCUS INFORMOU QUE TINHA OUTRA CONEXÃO NO MEMSO ENDEREÇO E CANCELOU POIS NÃO ESTAVA UTILIZANDO. MK NOME; CASA TELAS E CIA LTDA (LOJA 2) 38.454.719/0001-75 CONEXÃO ATIVA E ADIMPLENTE MARCUS VINICIUS XAVIER GONÇALVES (PROPRIETARIO) N/C HEITOR SIMAO GONCALVES (GERENTE) N/C GILCIMAR OLIVEIRA MENDONÇA (LOCADOR/PROPRIETARIO) N/C | S41: =IF(F41<TODAY(),"EXECUTADA",IF(F41=TODAY(),"EM EXECUÇÃO",IF(F41=TODAY()+1,"VALIDAR HOJE",IF(F41>TODAY()+1,"VALIDAR DEPOIS","-")))) -> EXECUTADA
A42: MUD END GIOVANA ROSA DE OLIVEIRA MARCELINO ALVES PROT:2604.1788 DINHEIRO (JHONATAN) - NOSSA SENHORA DAS GRAÇAS *PODE ANTECIPAR ATÉ 12H* | B42: MUD END | D42: VALIDAÇÃO OK ENVIAR AO CADASTRO | E42: 34998840375 | F42: 46119 | G42: =PROPER(TEXT(F42,"DDD")) -> Ter | H42: 0.41666667 | I42: DINHEIRO | J42: ENDEREÇO NOVO: RUA PEDRO QUIRINO DA SILVA, 1105 COMPLEMENTO: CASA 03 CEP: 38402075 BAIRRO: NOSSA SENHORA DAS GRAÇAS | K42: <b>ONT = ONT TP LINK 530 // CONECTOR = VERDE.</b> | L42: =IF(B42="MUD END","NÃO","SIM") -> NÃO | M42: - | N42: SIM | O42: - | P42: - | Q42: COMPROVANTE DE ENDEREÇO (DMAE) EM ANEXO NOME NO COMPROVANTE: LEONARDO REZENDE SILVA (DISSE QUE É O PROPRIETÁRIO DA CASA) | R42: MK END -> BRUNO LOPES CARDOSO: SOLICITAÇÃO DE ADESÃO RECUSADA EM 02/2026 MK NOMES -> GIOVANA ROSA DE OLIVEIRA MARCELINO ALVES (ASSINANTE DA CONEXÃO) -> LEONARDO REZENDE SILVA (DISSE QUE É O PROPRIETÁRIO): N/C | S42: =IF(F42<TODAY(),"EXECUTADA",IF(F42=TODAY(),"EM EXECUÇÃO",IF(F42=TODAY()+1,"VALIDAR HOJE",IF(F42>TODAY()+1,"VALIDAR DEPOIS","-")))) -> EXECUTADA
A43: MUD END CARLOS ANTONIO AMARAL PROT:2604.1964 PIX (JHONATAN) - GÁVEA **PRÉDIO COM PRUMADA** | B43: MUD END | D43: INFORMAÇÃO SOBRE COMPROVANTE DE RESIDENCIA INCORRETO ENDEREÇO NÃO ALTERADO | E43: 34999601750 | F43: 46119 | G43: =PROPER(TEXT(F43,"DDD")) -> Ter | H43: 0.54166667 | I43: PIX | J43: ENDEREÇO NOVO: AVENIDA NICOMEDES ALVES DOS SANTOS, 6611 COMPLEMENTO: AP 201 BLOCO 2 CEP: 38411869 BAIRRO: GÁVEA | K43: <b>ONT = ONT TP LINK 220 // CONECTOR = VERDE.</b> | L43: =IF(B43="MUD END","NÃO","SIM") -> NÃO | M43: - | N43: SIM | O43: - | P43: - | Q43: COMPROVANTE DE ENDEREÇO (CONTRATO DE COMPRA E VENDA) EM ANEXO NOME NO COMPROVANTE: CARLOS ANTONIO AMARAL (ASSINANTE) | R43: MK END N/C ______________________________________________________________________________ MK NOMES -> CARLOS ANTONIO AMARAL (COMPRADOR / RESPONSÁVEL PELO IMÓVEL): ASSINANTE DA CONEXÃO -> RONALDO ALBERTINO CANDIDO JUNIOR (VENDEDOR / ANTIGO RESPONSÁVEL PELO IMÓVEL): N/C -> MATHEUS DIAS MATOS (PROPRIETÁRIO DO VEÍCULO UTILIZADO NA NEGOCIAÇÃO): N/C -> JÚLIA PLACIDIO MEDEIROS SILVA (RECEBEDORA DO VALOR VIA PIX): N/C -> CAIXA ECONÔMICA FEDERAL (AGENTE FINANCEIRO DO IMÓVEL): N/C | S43: =IF(F43<TODAY(),"EXECUTADA",IF(F43=TODAY(),"EM EXECUÇÃO",IF(F43=TODAY()+1,"VALIDAR HOJE",IF(F43>TODAY()+1,"VALIDAR DEPOIS","-")))) -> EXECUTADA
A44: MUD END LEONARDO APARECIDO ARAUJO MARIANO PROT:2604.714 CARTAO (PEDRO) - JARDIM HOLANDA *TROCAR ONT POR UMA ONU (CLIENTE IRÁ USAR ROTEADOR PRÓPRIO)* | B44: MUD END | D44: VALIDAÇÃO OK ENVIAR AO CADASTRO | E44: 34998882510 | F44: 46119 | G44: =PROPER(TEXT(F44,"DDD")) -> Ter | H44: 0.54166667 | I44: CARTÃO | J44: ENDEREÇO NOVO: ALAMEDA JOSÉ DE OLIVEIRA, 990 COMPLEMENTO: CASA 5 CEP: 38412880 BAIRRO: JARDIM HOLANDA | K44: <b>ONT = ONT TP LINK 530 // CONECTOR = VERDE.</b> | L44: =IF(B44="MUD END","NÃO","SIM") -> NÃO | M44: - | N44: SIM | O44: - | P44: - | Q44: COMPROVANTE DE ENDEREÇO (CEMIG) EM ANEXO NOME NO COMPROVANTE: LEONARDO APARECIDO ARAUJO (ASSINANTE) | R44: MK END: N/C MK NOME: LEONARDO APARECIDO ARAUJO MARIANO (TITULAR) - CLIENTE POSSUI CONEXÃO CONOSCO DESDE 03/2025, ATIVA E ADIMPLENTE | S44: =IF(F44<TODAY(),"EXECUTADA",IF(F44=TODAY(),"EM EXECUÇÃO",IF(F44=TODAY()+1,"VALIDAR HOJE",IF(F44>TODAY()+1,"VALIDAR DEPOIS","-")))) -> EXECUTADA
A45: KETLIN GERALDA DE SOUZA DA SILVA (SALAO ESPACO GIRASSOL) - GABRIEL | D45: verificando se vai permanecer na agenda | F45: 46119 | G45: =PROPER(TEXT(F45,"DDD")) -> Ter | H45: 0.625 | L45: =IF(B45="MUD END","NÃO","SIM") -> SIM | S45: =IF(F45<TODAY(),"EXECUTADA",IF(F45=TODAY(),"EM EXECUÇÃO",IF(F45=TODAY()+1,"VALIDAR HOJE",IF(F45>TODAY()+1,"VALIDAR DEPOIS","-")))) -> EXECUTADA
A46: MUD END SHAUAN SOARES RODRIGUES RAMOS PROT:2604.1929 CARTAO (RONALD) - PLANALTO | B46: MUD END | D46: VALIDAÇÃO OK ENVIAR AO CADASTRO | E46: 38999557160 | F46: 46119 | G46: =PROPER(TEXT(F46,"DDD")) -> Ter | H46: 0.625 | I46: CARTÃO | J46: ENDEREÇO NOVO: RUA JORGE CAUHY, 32 COMPLEMENTO: CASA 4 CEP: 38413216 BAIRRO: PLANALTO | K46: <b>ONU = DATA // CONECTOR = VERDE.</b> | L46: =IF(B46="MUD END","NÃO","SIM") -> NÃO | M46: - | N46: SIM | O46: - | P46: - | Q46: COMPROVANTE DE ENDEREÇO (CONTRATO DE LOCAÇÃO) EM ANEXO NOME NO COMPROVANTE: SHAUAN SOARES RODRIGUES RAMOS (ASSINANTE) | R46: MK END; YELITZA DEL CARMEN LEZAMA CAIXETA 014.163.236-43 CONEXÃO NA CASA 08 CANCELADA E EQUIPAMENTOS DEVOLVIDOS, SEM DEBITOS PENDENTES ALAIR CECILIO RIBEIRO 006.189.478-84 CONEXÃO NA CASA 07 CANCELADA E EQUIPAMENTOS DEVOLVIDOS, SEM DEBITOS PENDENTES MK NOME; PRICILA NUNES DA SILVA (NAMORADA) 149.885.416-81 N/C SILVIA LETICIA R. VELOSO 128.051.916-92 (TESTEMUNHA) CLIENTE MZ NET COM CONEXÃO ATIVA E ADIMPLENTE MARIA APARECIDA FERREIRA 753.807.736-72 (LOCADORA) N/C GILMA ALMEIDA DE OLIVEIRA 333.236.661-00 (ADMINISTRAÇÃO) N/C | S46: =IF(F46<TODAY(),"EXECUTADA",IF(F46=TODAY(),"EM EXECUÇÃO",IF(F46=TODAY()+1,"VALIDAR HOJE",IF(F46>TODAY()+1,"VALIDAR DEPOIS","-")))) -> EXECUTADA
A47: MUD END MARCELO MARTINS SILVA PROT:2603.36108 DINHEIRO (VITOR M.) - PRESIDENTE ROOSEVELT // COM FIBRA EXISTENTE | B47: MUD END | D47: CONFERENCIA INCOMPLETA. | E47: 34984006345 | F47: 46119 | G47: =PROPER(TEXT(F47,"DDD")) -> Ter | H47: 0.70833333 | I47: DINHEIRO | J47: ENDEREÇO NOVO: RUA FRANCISCO VIEIRA DE PAIVA, 60 COMPLEMENTO: CASA 2 CEP: 38401002 BAIRRO: PRESIDENTE ROOSEVELT | K47: <b>ONU = DATA // CONECTOR = VERDE.</b> | L47: =IF(B47="MUD END","NÃO","SIM") -> NÃO | M47: - | N47: SIM | O47: - | P47: - | Q47: COMPROVANTE DE ENDEREÇO (CEMIG) EM ANEXO NOME NO COMPROVANTE: ACACIO ALVES (ASSINANTE DISSE SER DONO DA RESIDENCIA) | R47: MK NOME: ACACIO ALVES (DONO DA RESIDENCIA): N/C MK END: DIEGO SANTOS DA SILVA: NEGADO PELO CADASTRO. VITORIA LAYSSA EDUARDO - REPROVADO CADASTRO | S47: =IF(F47<TODAY(),"EXECUTADA",IF(F47=TODAY(),"EM EXECUÇÃO",IF(F47=TODAY()+1,"VALIDAR HOJE",IF(F47>TODAY()+1,"VALIDAR DEPOIS","-")))) -> EXECUTADA
A48: MUD END + ALT PLANO NADIR ROMANIO ABRANTES PROT:2604.1117 ISENTO (PEDRO) - LOTEAMENTO LUIZOTE DE FREITAS IV // | B48: MUD END + ALT PLAN | D48: NECESSÁRIO FOTO DO COMPROVANTE POR COMPLETO SEM CONFERENCIAS | E48: 34988346869 | F48: 46119 | G48: =PROPER(TEXT(F48,"DDD")) -> Ter | H48: 0.70833333 | I48: ISENTO | J48: ENDEREÇO NOVO: RUA VEREADORA DRIKA PROTETORA, 176 COMPLEMENTO: CASA ÚNICA CEP: 38418529 BAIRRO: LOTEAMENTO LUIZOTE DE FREITAS IV | K48: <b>ONU = DATA // CONECTOR = VERDE.</b> | L48: =IF(B48="MUD END","NÃO","SIM") -> SIM | M48: PLANO ATUAL: 600 MEGA/79,90 CONTRATADO EM 06/2025 COM FIDELIDADE DE 12 MESES. ROTEADOR: HUAWEI AX2 PLANO OFERTADO: 600 MEGA/79,90. BENEFÍCIOS: ACESSO GRATUITO AO APP MZTV (CDNTV+) | N48: SIM | O48: - | P48: - | Q48: COMPROVANTE DE ENDEREÇO (CEMIG) EM ANEXO NOME NO COMPROVANTE: WESLEY VITAL SILVA (DISSE SER O DONO DO IMÓVEL) | R48: MK END: N/C MK NOME: WESLEY VITAL SILVA (DISSE SER O DONO DO IMÓVEL) - N/C NADIR ROMANIO ABRANTES (TITULAR) - POSSUI CONEXÃO CONOSCO DESDE 06/2025, ATIVA E ADIMPLENTE. | S48: =IF(F48<TODAY(),"EXECUTADA",IF(F48=TODAY(),"EM EXECUÇÃO",IF(F48=TODAY()+1,"VALIDAR HOJE",IF(F48>TODAY()+1,"VALIDAR DEPOIS","-")))) -> EXECUTADA
A49: MUD END + ALT PLANO JANAINE NOBRE ROCHA PROT:2604.3325. ISENTO (LAUREN) - BOSQUE DOS BURITIS // *PODE ANTECIPAR* *LIGAR ANTES DE IR* *IR AS 15:30 HORAS* | B49: MUD END + ALT PLAN | D49: VALIDAÇÃO OK ENVIAR AO CADASTRO | E49: 34997725400 | F49: 46119 | G49: =PROPER(TEXT(F49,"DDD")) -> Ter | H49: 0.625 | I49: ISENTO | J49: ENDEREÇO NOVO: ALAMEDA CASTANHEIRAS, 152 COMPLEMENTO: CASA 1 CEP: 3840657 BAIRRO: BOSQUE DOS BURITIS | K49: <b>ONT = ONT TP LINK 220 // CONECTOR = VERDE.</b> | L49: =IF(B49="MUD END","NÃO","SIM") -> SIM | M49: PLANO ATUAL: 300 MEGA/69,90 CONTRATADO EM 08/2024 COM FIDELIDADE DE 12 MESES. ROTEADOR: ONT TP-LINK XC220 PLANO OFERTADO: 600 MEGA/79,90. BENEFÍCIOS: ACESSO GRATUITO AO APP MZTV (CDNTV+) | N49: NÃO | O49: ADRIEL (ESPOSO DE JANAINE) | P49: 34-991865089 | Q49: COMPROVANTE DE ENDEREÇO (CONTRATO DE LOCAÇÃO) EM ANEXO NOME NO COMPROVANTE: ADRIEL JOSE MENDES (DIZ SER SEU ESPOSO) | R49: MK END - N/C MK NOMES - CIRO YUJI ESTEVES (LOCADOR) CPF : 344.210.548-01 - N/C c (DIZ SER ESPOSO DE JANAINE) CPF: 087.806.546-65 - N/C | S49: =IF(F49<TODAY(),"EXECUTADA",IF(F49=TODAY(),"EM EXECUÇÃO",IF(F49=TODAY()+1,"VALIDAR HOJE",IF(F49>TODAY()+1,"VALIDAR DEPOIS","-")))) -> EXECUTADA
A50: MUD END DARLENE GOMES PEREIRA PROT:2604.1449 CARTÃO (RAMONY) - MORUMBI | B50: MUD END | D50: VALIDAÇÃO OK ENVIAR AO CADASTRO | E50: 34996662547 | F50: 46120 | G50: =PROPER(TEXT(F50,"DDD")) -> Qua | H50: 0.33333333 | I50: CARTÃO | J50: ENDEREÇO NOVO: RUA ARRUDA, 525 COMPLEMENTO: CASA UNICA CEP: 38407129 BAIRRO: MORUMBI | K50: <b>ONU = DATA // CONECTOR = VERDE.</b> | L50: =IF(B50="MUD END","NÃO","SIM") -> NÃO | M50: - | N50: NÃO | O50: GERALDO BATISTA DE SOUZA (SOGRO) | P50: 34 98871-3589 | Q50: COMPROVANTE DE ENDEREÇO (CEMIG) EM ANEXO. NOME NO COMPROVANTE: GERALDO BATISTA DE SOUZA (SOGRO) | R50: MK END: N/C MK NOME: GERALDO BATITA DE SOUZA(DISSE SER SEU SOGRO) - N/C | S50: =IF(F50<TODAY(),"EXECUTADA",IF(F50=TODAY(),"EM EXECUÇÃO",IF(F50=TODAY()+1,"VALIDAR HOJE",IF(F50>TODAY()+1,"VALIDAR DEPOIS","-")))) -> EXECUTADA
A51: MUD END + ALT PLANO MARIA APARECIDA XAVIER DE SOUSA (CIDA XAVIER HAIRS) PROT:2604.739 ISENTO (PEDRO) - JARDIM PATRÍCIA // *TROCA DE EQUIPAMENTO* | B51: MUD END + ALT PLAN | D51: VALIDAÇÃO OK ENVIAR AO CADASTRO COBRAR ASSINATURA DO CONTRATO | E51: 34996819712 | F51: 46120 | G51: =PROPER(TEXT(F51,"DDD")) -> Qua | H51: 0.33333333 | I51: ISENTO | J51: ENDEREÇO NOVO: AVENIDA JUHEN CECÍLIO JORGE, 525 COMPLEMENTO: LOJA 2 CEP: 38414096 BAIRRO: JARDIM PATRÍCIA | K51: <b>ONU = DATA // CONECTOR = VERDE.</b> | L51: =IF(B51="MUD END","NÃO","SIM") -> SIM | M51: PLANO ATUAL: 600 MEGA/79,90 CONTRATADO EM 05/2025 COM FIDELIDADE DE 12 MESES. ROTEADOR: TP LINK G-5 PLANO OFERTADO: 600 MEGA/79,90. BENEFÍCIOS: ACESSO GRATUITO AO APP MZTV (CDNTV+) | N51: SIM | O51: - | P51: - | Q51: COMPROVANTE DE ENDEREÇO (DMAE) EM ANEXO NOME NO COMPROVANTE: EDMAR FERNANDES PEREIRA (DISSE SER O DONO DO IMÓVEL) | R51: MK END: HNQ NOMURA COMERCIO LTDA(EMPORIO GOMES) / COMPLEMENTO LOJA 1 - POSSUI CONEXÃO CONOSCO DESDE 06/2025, ATIVA E ADIMPLENTE. JOSE DOS ANJOS GOMES DA COSTA (EMPORIO GOMES) - CADASTRO CANCELADO, POSSUIA CONEXÃO CONOSCO DESDE 05/2022, PORÉM EM 06/2025 REALIZOU A TROCA DE TITULARIDADE PARA O CADASTRO DO HNQ NOMURA COMERCIO LTDA(EMPORIO GOMES). DJEANE VIEIRA FUKUDA (STUDIO DJEANE FUKUDA) - CONEXÃO CANCELADA POR INADIMPLÊNCIA EM 09/2025, CLIENTE SEGUE COM PENDÊNCIAS DESDE ENTÃO (MENSALIDADES, MULTA DE QUEBRA DE CONTRATO E DEVOLUÇÃO DOS EQUIPAMENTOS). (R$1.039,70) MK NOME: EDMAR FERNANDES PEREIRA (DISSE SER O DONO DO IMÓVEL) - N/C MARIA APARECIDA XAVIER DE SOUSA (CIDA XAVIER HAIRS) (TITULAR) - POSSUI CONEXÃO CONOSCO DESDE 04/2025, ATIVA E ADIMPLENTE. OBS.: EM RELAÇÃO AOS EQUIPAMENTOS QUE A CLIENTE DJEANE VIEIRA FUKUDA (STUDIO DJEANE FUKUDA) NÃO REALIZOU A DEVOLUÇÃO, FOI INFORMADO PELA CLIENTE QUE HÁ EQUIPAMENTOS DA EMPRESA NO LOCAL, OS QUAIS PODEM CORRESPONDER AOS EQUIPAMENTOS VINCULADOS A ESTE CADASTRO. | S51: =IF(F51<TODAY(),"EXECUTADA",IF(F51=TODAY(),"EM EXECUÇÃO",IF(F51=TODAY()+1,"VALIDAR HOJE",IF(F51>TODAY()+1,"VALIDAR DEPOIS","-")))) -> EXECUTADA
A52: MUD END REJANE DE LIMA JESUS PROT:2604.2815 PIX (PEDRO) - SANTA ROSA *PODE ANTECIPAR* | B52: MUD END | D52: PENDENTE MENSALIDADE DEMAIS CONFERENCIAS OK | E52: 34984479701 | F52: 46120 | G52: =PROPER(TEXT(F52,"DDD")) -> Qua | H52: 0.33333333 | I52: PIX | J52: ENDEREÇO NOVO: RUA EMÍLIA FERNANDES DE BRITO, 400 COMPLEMENTO: CASA FRENTE CEP: 38401768 BAIRRO: SANTA ROSA | K52: <b>ONT = ONT TP LINK 530 // CONECTOR = VERDE.</b> | L52: =IF(B52="MUD END","NÃO","SIM") -> NÃO | Q52: COMPROVANTE DE ENDEREÇO (CONTRATO DE LOCAÇÃO) EM ANEXO NOME NO COMPROVANTE: REJANE DE LIMA JESUS (ASSINANTE) | R52: MK END: N/C MK NOME: SERGIO DOS SANTOS GUIMARAES (LOCADOR) - N/C REJANE DE LIMA JESUS (LOCATÁRIA / TITULAR) - POSSUI CONEXÃO CONOSCO DESDE 12/2025, ATIVA E ADIMPLENTE. | S52: =IF(F52<TODAY(),"EXECUTADA",IF(F52=TODAY(),"EM EXECUÇÃO",IF(F52=TODAY()+1,"VALIDAR HOJE",IF(F52>TODAY()+1,"VALIDAR DEPOIS","-")))) -> EXECUTADA
A53: MUD END + ALT PLANO LORENA BRITO COSTA PROT:2604.3382 ISENTO (RONALD) - MANSOUR // *TROCA DE EQUIPAMENTO* | B53: MUD END + ALT PLAN | D53: VALIDAÇÃO OK ENVIAR AO CADASTRO COBRAR ASSINATURA DO CONTRATO | E53: 34998787957 | F53: 46120 | G53: =PROPER(TEXT(F53,"DDD")) -> Qua | H53: 0.33333333 | I53: ISENTO | J53: ENDEREÇO NOVO: RUA RIO PARANOÁ, 103 COMPLEMENTO: CASA UNICA CEP: 38414494 BAIRRO: MANSOUR | K53: . <b>ONU = DATA // CONECTOR = VERDE.</b> | L53: =IF(B53="MUD END","NÃO","SIM") -> SIM | M53: PLANO ATUAL: 1000 MEGA/99,90 CONTRATADO EM 04/2024 COM FIDELIDADE DE 12 MESES. ROTEADOR: ZTE H199-A PLANO OFERTADO: 1 GIGA (1.000 MEGA) R$99,90. BENEFÍCIOS: ACESSO GRATUITO AO APP MZTV (CDNTV+) + VOD | N53: SIM | O53: - | P53: - | Q53: COMPROVANTE DE ENDEREÇO (CEMIG) EM ANEXO NOME NO COMPROVANTE: ODAIR JOSE CUSTODIO DA SILVA (ANTIGO INQUILINO) | R53: MK END; MICHELLY MARIA DE OLIVEIRA CONEXÃO CANCELADA EM 02/2020 DEVIDO A MENSALIDADES EM ABERTO, EQUIPAMENTOS RECOLHIDOS PORÉM DÉBITOS NÃO FORAM PAGOS. (R$1.178,70) MK NOME; LORENA BRITO COSTA 063.392.226-92 (ASSINANTE) CONEXÃO ATIVA E CLIENTE ADIMPLENTE ODAIR JOSE CUSTODIO DA SILVA 979.2**.***-** (ANTIGO INQUILINO) N/C | S53: =IF(F53<TODAY(),"EXECUTADA",IF(F53=TODAY(),"EM EXECUÇÃO",IF(F53=TODAY()+1,"VALIDAR HOJE",IF(F53>TODAY()+1,"VALIDAR DEPOIS","-")))) -> EXECUTADA
A54: MUD END + ALT PLANO CRISTINA VETTORAZZI PROT:2604.1226 ISENTO (PEDRO) - JARDIM BRASÍLIA **PRÉDIO COM PRUMADA** // | B54: MUD END + ALT PLAN | D54: PENDENTE TEXTO SOBRE COMPROVANTE DE RESIDENCIA COBRAR ASSINATURA DO CONTRATO | E54: 38999909458 | F54: 46120 | G54: =PROPER(TEXT(F54,"DDD")) -> Qua | H54: 0.41666667 | I54: ISENTO | J54: ENDEREÇO NOVO: RUA ALAOR CARLOS GARCIA, 455 COMPLEMENTO: COND. RESIDENCIAL JARDIM BRASÍLIA - BL.03, APT.904 CEP: 38401883 BAIRRO: JARDIM BRASÍLIA | K54: <b>ONT = ONT TP LINK 530 // CONECTOR = VERDE.</b> | L54: =IF(B54="MUD END","NÃO","SIM") -> SIM | M54: PLANO ATUAL: 600 MEGA/79,90 CONTRATADO EM 04/2025 COM FIDELIDADE DE 12 MESES. ROTEADOR: ONT TP-LINK X530 PLANO OFERTADO: 600 MEGA/79,90. BENEFÍCIOS: ACESSO GRATUITO AO APP MZTV (CDNTV+) | N54: NÃO | O54: PAULO CEZAR (MARIDO) | P54: 38999570854 | Q54: COMPROVANTE DE ENDEREÇO (CONTRATO DE COMPRA E VENDA) EM ANEXO NOME NO COMPROVANTE: CRISTINA VETTORAZZI (ASSINANTE) | R54: MK END: N/C MK NOME: CAIXA ECONÔMICA FEDERAL (CREDORA FIDUCIÁRIA) - N/C OPÇÃO EMPREENDIMENTOS IMOBILIÁRIOS EIRELI (ALIENANTE/CONSTRUTORA/INCORPORADORA) - N/C CRISTINA VETTORAZZI (ADQUIRENTE / TITULAR) - POSSUI CONEXÃO CONOSCO DESDE 04/2025, ATIVA E ADIMPLENTE. JOÃO PAULO NAVES CAMARGO (ADMINISTRADOR DA OPÇÃO EMPREENDIMENTOS) - N/C CLAUDIA CRISTINA FERREIRA FRANCO MELO (REPRESENTANTE DA CAIXA ECONÔMICA FEDERAL) - N/C LUIZ EUGÊNIO DA FONSECA (OFICIAL REGISTRADOR) - N/C JOSÉ FONSECA E SILVA NETO (REGISTRADOR SUBSTITUTO) - N/C MELISSA SOARES FONSECA (REGISTRADORA SUBSTITUTA) - N/C IRENO VETTORAZZI (PAI DA TITULAR) - N/C IRACI CRISTINA VETTORAZZI (MÃE DA TITULAR) - N/C | S54: =IF(F54<TODAY(),"EXECUTADA",IF(F54=TODAY(),"EM EXECUÇÃO",IF(F54=TODAY()+1,"VALIDAR HOJE",IF(F54>TODAY()+1,"VALIDAR DEPOIS","-")))) -> EXECUTADA
A55: MUD END ARAMIS ARAUJO DE OLIVEIRA PROT:2604.2013 PIX (RAMONY) - LOTEAMENTO RESIDENCIAL PEQUIS | B55: MUD END | D55: VALIDAÇÃO OK ENVIAR AO CADASTRO | E55: 34996716531 | F55: 46120 | G55: =PROPER(TEXT(F55,"DDD")) -> Qua | H55: 0.41666667 | I55: PIX | J55: ENDEREÇO NOVO: RUA DO AZULÃO, 336 COMPLEMENTO: CASA UNICA CEP: 38421040 BAIRRO: LOTEAMENTO RESIDENCIAL PEQUIS | K55: <b>ONT = ONT TP LINK 530 // CONECTOR = VERDE.</b> | L55: =IF(B55="MUD END","NÃO","SIM") -> NÃO | M55: - | N55: SIM | O55: NAELLEN (ESPOSA DE ARAMIS) | P55: 37 98821-2455 | Q55: COMPROVANTE DE ENDEREÇO (CEMIG) EM ANEXO. NOME NO COMPROVANTE: KELLEN ALVES PIRES (PROPRIETÁRIA DO IMÓVEL) COMPROVANTE DE ENDEREÇO (CONTRATO DE LOCAÇÃO) EM ANEXO. NOME NO DOCUMENTO: NAELLEN APARECIDA DOMINGOS (ESPOSA ARAMIS) | R55: MK END: N/C MK NOMES: LOCADORA KELLEN ALVES PIRES / CPF: 111.909.216-77 PROPRIETÁRIA DO IMÓVEL - N/C LOCATÁRIA NAELLEN APARECIDA DOMINGOS / CPF: 113.645.766-60 ESPOSA DO TITULAR - N/C | S55: =IF(F55<TODAY(),"EXECUTADA",IF(F55=TODAY(),"EM EXECUÇÃO",IF(F55=TODAY()+1,"VALIDAR HOJE",IF(F55>TODAY()+1,"VALIDAR DEPOIS","-")))) -> EXECUTADA
A56: MUD END MAURO SERGIO SANTANA MAIA PROT:2604.5462 PIX (ANDREZA) - JARDIM HOLANDA **PRÉDIO COM PRUMADA** | B56: MUD END | D56: VALIDAÇÃO OK ENVIAR AO CADASTRO | E56: 38991304709 | F56: 46120 | G56: =PROPER(TEXT(F56,"DDD")) -> Qua | H56: 0.41666667 | I56: PIX | J56: ENDEREÇO NOVO: ALAMEDA JOSÉ DE OLIVEIRA GUIMARÃES, 700 COMPLEMENTO: COND. UNITED KINGDOM - BLOCO 11, APTO 203 CEP: 38412324 BAIRRO: JARDIM HOLANDA | K56: <b>ONT = ONT ZTE // CONECTOR = VERDE.</b> | L56: =IF(B56="MUD END","NÃO","SIM") -> NÃO | M56: - | N56: NÃO | O56: MANY GALT MOURA NASCIMENTO (CUNHADO) | P56: 34998927532 | Q56: COMPROVANTE DE ENDEREÇO (CONTRATO DE LOCAÇÃO) EM ANEXO NOME NO COMPROVANTE: YNGRYD TURY MOURA SILVA (ESPOSA DO ASSINANTE) | R56: MK END: N/C ________________________________________ MK NOMES: -> EUCILENE CORDEIRO DO NASCIMENTO (LOCADORA) - CPF 080.905.926-60: N/C -> YNGRYD YURY MOURA SILVA (LOCATÁRIA/ESPOSA DO ASSINANTE) - CPF 132.580.916-09: SOLICITAÇÃO DE ADESÃO EM 09/2025 APROVADA PARA O ESPOSO MAURO DE SANTANA MAIA. -> DENISE MOURA BARBOSA (TESTEMUNHA) - CPF 783.864.896-34: N/C -> MANY GALT MOURA NASCIMENTO (CUNHADO): N/C | S56: =IF(F56<TODAY(),"EXECUTADA",IF(F56=TODAY(),"EM EXECUÇÃO",IF(F56=TODAY()+1,"VALIDAR HOJE",IF(F56>TODAY()+1,"VALIDAR DEPOIS","-")))) -> EXECUTADA
A57: MUD END SUELEN LADEIA DA SILVA PROT:2603.24215 CARTÃO (VICTOR H.) - JARDIM PATRÍCIA **PRÉDIO COM PRUMADA** | B57: MUD END | D57: PENDENTE COMPROVANTE DEMAIS INFORMAÇÕES CONFERIDAS | E57: 34996993907 | F57: 46120 | G57: =PROPER(TEXT(F57,"DDD")) -> Qua | H57: 0.54166667 | I57: CARTÃO | J57: ENDEREÇO NOVO: RUA JOÃO RODRIGUES DE CASTRO, 55 COMPLEMENTO: PARQUE TRILHAS DA SERRA BL. 15, APTO 403 CEP: 38414122 BAIRRO: JARDIM PATRÍCIA | K57: <b>ONT = ONT TP LINK 230 // CONECTOR = VERDE.</b> | L57: =IF(B57="MUD END","NÃO","SIM") -> NÃO | M57: - | N57: NÃO | O57: POLIANA IDELFONSO FERREIRA DA SILVA (ESPOSA) | P57: 3499896-7464 | Q57: COMPROVANTE DE ENDEREÇO (DMAE) EM ANEXO NOME NO COMPROVANTE: POLIANA IDELFONSO FERREIRA DA SILVA (ESPOSA) | R57: MK NOMES : POLIANA IDELFONSO FERREIRA DA SILVA (ESPOSA) N/C MK END: N/C | S57: =IF(F57<TODAY(),"EXECUTADA",IF(F57=TODAY(),"EM EXECUÇÃO",IF(F57=TODAY()+1,"VALIDAR HOJE",IF(F57>TODAY()+1,"VALIDAR DEPOIS","-")))) -> EXECUTADA
A58: MUD END KAMILA DOS SANTOS SILVA PROT:2604.2649 CARTÃO (BRUNA) - JARDIM PATRÍCIA **PRÉDIO COM PRUMADA** // *PODE ANTECIPAR* | B58: MUD END | D58: VALIDAÇÃO OK ENVIAR AO CADASTRO | E58: 34991469011 | F58: 46120 | G58: =PROPER(TEXT(F58,"DDD")) -> Qua | H58: 0.54166667 | I58: CARTÃO | J58: ENDEREÇO NOVO: AVENIDA DOS EUCALIPTOS, 1000 COMPLEMENTO: BL 4 AP 1507 CEP: 38414123 BAIRRO: JARDIM PATRÍCIA | K58: <b>ONT = ONT TP LINK 530 // CONECTOR = VERDE.</b> | L58: =IF(B58="MUD END","NÃO","SIM") -> NÃO | M58: - | N58: NÃO | O58: JOAO PEDRO LOPES SOUSA (ESPOSO) | P58: 34 991723243 | Q58: COMPROVANTE DE ENDEREÇO (CONTRATO DE LOCAÇÃO) EM ANEXO NOME NO COMPROVANTE: JOAO PEDRO LOPES SOUSA (DIZ SER SEU ESPOSO) | R58: MK END: N/C MK NOMES: CLEITON DO SANTOS COELHO (LOCADOR): N/C IVAN NEGÓCIOS IMOBILIÁRIOS LTDA (ADMINISTRADORA):N/C IVAN GRACIANO DA COSTA FILHO (SÓCIO GERENTE):N/C RICARDO GRACIANO DA COSTA (ADVOGADO/REPRESENTANTE):N/C VICENTE PAULO FERREIRA (PROCURADOR):N/C JOYCE APARECIDA DIAS (PROCURADORA): N/C TAIZ LAMARA BALESTERE TEIXEIRA ALVES (PROCURADORA):N/C JOAO PEDRO LOPES SOUSA (LOCATÁRIO/ESPOSO DE KAMILA): N/C PORTO SEGURO CIA. DE SEGUROS GERAIS (SEGURADORA):N/C SPC (PROTEÇÃO AO CRÉDITO): N/C SERASA ( PROTEÇÃO AO CRÉDITO):N/C | S58: =IF(F58<TODAY(),"EXECUTADA",IF(F58=TODAY(),"EM EXECUÇÃO",IF(F58=TODAY()+1,"VALIDAR HOJE",IF(F58>TODAY()+1,"VALIDAR DEPOIS","-")))) -> EXECUTADA
A59: MUD END + ALT PLANO PATRICIA RODRIGUES LIMA PROT:2604.2198 ISENTO (BRUNA) - LARANJEIRAS // *PEND COMPROVATE DE END* *ASSINATURA PEND* | B59: MUD END + ALT PLAN | D59: VALIDAÇÃO OK ENVIAR AO CADASTRO | E59: (34) 99873-2569 | F59: 46120 | G59: =PROPER(TEXT(F59,"DDD")) -> Qua | H59: 0.625 | I59: ISENTO | J59: ENDEREÇO NOVO: RUA DO ADOLESCENTE, 363 COMPLEMENTO: CASA FUNDOS CEP: 38410302 BAIRRO: LARANJEIRAS | K59: <b>ONU = DATA // CONECTOR = VERDE.</b> | L59: =IF(B59="MUD END","NÃO","SIM") -> SIM | M59: PLANO ATUAL: 600 MEGA/79,90 CONTRATADO EM 03/25 COM FIDELIDADE DE 12 MESES. ROTEADOR: HUAWEI AX2 PLANO OFERTADO: 600 MEGA/79,90. BENEFÍCIOS: ACESSO GRATUITO AO APP MZTV (CDNTV+) | N59: NÃO | O59: VANESSA RODRIGUES LIMA (IRMÃ) | P59: 34 9 9894-1030 | Q59: COMPROVANTE DE ENDEREÇO (DMAE) EM ANEXO NOME NO COMPROVANTE: JOAO BATISTA DE LIMA NETO (PAI DA ASSINANTE) | R59: MK END E MK NOMES: JOAO BATISTA DE LIMA NETO (PAI DA ASSINANTE) CONTRATOU EM 11/2025, CONEXÃO ATIVA E ADIMPLENTE NO SEU CADASTRO NÃO POSSUI COMPLEMENTO EM SEU CADASTRO | S59: =IF(F59<TODAY(),"EXECUTADA",IF(F59=TODAY(),"EM EXECUÇÃO",IF(F59=TODAY()+1,"VALIDAR HOJE",IF(F59>TODAY()+1,"VALIDAR DEPOIS","-")))) -> EXECUTADA
A60: MUD END DEIVID ENNES CARIAO DOS SANTOS PROT:2604.2426 CARTAO (RONALD) - PATRIMÔNIO **PRÉDIO SEM PRUMADA - CTOE** *PODE ANTECIPAR* | B60: MUD END | D60: MENSALIDADE PENDENTE | E60: 34998808687 | F60: 46120 | G60: =PROPER(TEXT(F60,"DDD")) -> Qua | H60: 0.625 | I60: CARTÃO | J60: ENDEREÇO NOVO: RUA DA CARIOCA, 746 COMPLEMENTO: APT. 202 CEP: 38411046 BAIRRO: PATRIMÔNIO | K60: <b>ONT = ONT TP LINK 530 // CONECTOR = VERDE.</b> | L60: =IF(B60="MUD END","NÃO","SIM") -> NÃO | M60: - | N60: SIM | O60: - | P60: - | Q60: COMPROVANTE DE ENDEREÇO (CONTRATO DE LOCAÇÃO) EM ANEXO NOME NO COMPROVANTE: DEIVID ENNES CARIAO DOS SANTOS (ASSINANTE) | R60: MK END; N/C MK NOME; DEIVID ENNES CARIAO DOS SANTOS 130.122.227-58 (ASSINANTE) CONEXÃO ATIVA E CLIENTE ADIMPLENTE NATALIA DE PAIVA TAVARES CARIAO DOS SANTOS (CONJUGUE) N/C NIVEA PEREIRA DE LIMA (LOCADORA) N/C ARANTES NEGÓCIOS IMOBILIARIOS LTDA (PROCURADORA) N/C ARANTES SOLUÇÕES IMOBILIÁRIAS LTDA (PROCURADORA) N/C DIOGO BORGES NASCIMENTO (PROCURADOR) N/C ANNA LAURA OLIVEIRA DE CASTRO (TESTEMUNHA) N/C PRISCILLA DE MEDEIROS FARIA (TESTEMUNHA) N/C | S60: =IF(F60<TODAY(),"EXECUTADA",IF(F60=TODAY(),"EM EXECUÇÃO",IF(F60=TODAY()+1,"VALIDAR HOJE",IF(F60>TODAY()+1,"VALIDAR DEPOIS","-")))) -> EXECUTADA
A61: MUD END ELIDA CRISTINA DE MORAIS DORNELAS (SAMUEL/FILHO) PROT:2603.35275 PIX (VICTOR H.) - PLANALTO / NÃO ANTECIPAR | B61: MUD END | D61: VALIDAÇÃO OK ENVIAR AO CADASTRO | E61: 34997634832 | F61: 46120 | G61: =PROPER(TEXT(F61,"DDD")) -> Qua | H61: 0.70833333 | I61: PIX | J61: ENDEREÇO NOVO: AVENIDA INDAIÁ, 840 COMPLEMENTO: CASA 1 CEP: 38413111 BAIRRO: PLANALTO | K61: <b>ONT = ONT TP LINK 530 // CONECTOR = VERDE.</b> | L61: =IF(B61="MUD END","NÃO","SIM") -> NÃO | M61: - | N61: NÃO | O61: KAYLA DOS SANTOS (NORA) | P61: 34 9 9144 8410 | Q61: COMPROVANTE DE ENDEREÇO (CEMIG) EM ANEXO NOME NO COMPROVANTE: FABIO MOREIRA (DISSE SER SOGRO DO SEU FILHO SAMUEL) | R61: MK NOMES: FABIO MOREIRA (DISSE SER SOGRO DO SEU FILHO SAMUEL) CLIENTE DESDE 11/2025 - NO DIA DE HOJE CLIENTE ESTÁ EM REDUÇÃO DEVIDO MENSALIDADE EM ABERTO VENCIDA EM 10/03/2026 MORA NA CASA DOS FUNDOS NO MESMO ENDEREÇO QUE SAMUEL VAI SE MUDAR KAYLA DOS SANTOS (NORA DE ELIDA) N/C PELO PESSOAS E EMPRESAS DA CONEXÃO DE FABIO ESTÁ RENOMEADO COMO CARLA DOS SANTOS, N/C NOS DOIS NOMES MK END GILSON ISRAEL VENANCIO DE MEDEIROS CANCELADO POR INADIMPLENCIA EM 02/2026 DEBITOS : R$ 1222,70 SENDO: R$ 239,70 REFERENTE 3 MENSALIDADES EM ABERTO R$ 384,00 SOBRE MULTA CONTRATUAL R$ 599,00 REFERENTE ONT EMPRESTADA QUE NÃO DEVOLVEU | S61: =IF(F61<TODAY(),"EXECUTADA",IF(F61=TODAY(),"EM EXECUÇÃO",IF(F61=TODAY()+1,"VALIDAR HOJE",IF(F61>TODAY()+1,"VALIDAR DEPOIS","-")))) -> EXECUTADA
A62: MUD END JHULIO DE OLIVEIRA CORDEIRO PROT:2604.2829 PIX (RONALD) - TOCANTINS | B62: MUD END | D62: CORRIGIR COMPLEMENTO DO ENDEREÇO NA OS CLIENTE COM 2 MENSALIDADES EM ATRASO NA SEGUNDA CONEXÃO. | E62: 34991735658 | F62: 46120 | G62: =PROPER(TEXT(F62,"DDD")) -> Qua | H62: 0.70833333 | I62: PIX | J62: ENDEREÇO NOVO: RUA CAPITÃO DIOMAR MENEZES, 206 COMPLEMENTO: CASA FUNDO CEP: 38415318 BAIRRO: TOCANTINS | K62: <b>ONT = ONT TP LINK 530 // CONECTOR = VERDE.</b> | L62: =IF(B62="MUD END","NÃO","SIM") -> NÃO | M62: - | N62: NÃO | O62: ANA KAROLINE SOUSA SALES (ESPOSA) | P62: 34991735658 | Q62: COMPROVANTE DE ENDEREÇO (CEMIG) EM ANEXO NOME NO COMPROVANTE: FABIO DA ROCHA SALES (SOGRO DE JHULIO) | R62: MK END; JOSE HENRIQUE VIEIRA DOS SANTOS 123.290.574-74 CONEXÃO CANCELADA EM 10/2021 POR MENSALIDADES EM ATRASO, EM 01/2025 TITULAR ENTROU EM CONTATO E REALIZOU ACORDO E PAGAMENTO DOS DÉBITOS PENDENTES. FABIO DA ROCHA SALES (SOGRO DE FABIO) NÃO LOCALIZADO INFORMAÇÕES SOBRE O CLIENTE MK NOME; JHULIO DE OLIVEIRA CORDEIRO 120.243.456-89 CLIENTE MZ NET COM DUAS CONEXÕES, A QUE ESTÁ SE MUDANDO ADIMPLENTE, PORÉM A SEGUNDA (JHULIO DE OLIVEIRA CORDEIRO (TABACARIA PAJÉ)) CONEXÃO INADIPLENTE 2 MENSALIDADES EM ABERTO. | S62: =IF(F62<TODAY(),"EXECUTADA",IF(F62=TODAY(),"EM EXECUÇÃO",IF(F62=TODAY()+1,"VALIDAR HOJE",IF(F62>TODAY()+1,"VALIDAR DEPOIS","-")))) -> EXECUTADA
A63: MUD END + ALT PLANO BEATRYS REGINA BARBOSA SILVA PROT:2604.4843 ISENTO (ANDREZA) - RESIDENCIAL INTEGRAÇÃO // | B63: MUD END + ALT PLAN | D63: VALIDAÇÃO OK ENVIAR AO CADASTRO COBRAR ASSINATURA DO CONTRATO | E63: 34991502141 | F63: 46121 | G63: =PROPER(TEXT(F63,"DDD")) -> Qui | H63: 0.33333333 | I63: ISENTO | J63: ENDEREÇO NOVO: RUA MANUEL LÚCIO, 455 COMPLEMENTO: CASA FRENTE CEP: 38407589 BAIRRO: RESIDENCIAL INTEGRAÇÃO | K63: . <b>ONU = DATA // CONECTOR = VERDE.</b> | L63: =IF(B63="MUD END","NÃO","SIM") -> SIM | M63: PLANO ATUAL: 600 MEGA/79,90 CONTRATADO EM 06/2025 COM FIDELIDADE DE 12 MESES. ROTEADOR: HUAWEI AX2 PLANO OFERTADO: 600 MEGA/79,90. BENEFÍCIOS: ACESSO GRATUITO AO APP MZTV (CDNTV+) | N63: SIM | O63: - | P63: - | Q63: COMPROVANTE DE ENDEREÇO (MULTA DE TRÂNSITO) EM ANEXO NOME NO COMPROVANTE: JONATAN DOS SANTOS (DISSE QUE É O ANTIGO INQUILINO DO IMÓVEL) | R63: MK END: N/C ________________________________________ MK NOMES: -> JONATAN DOS SANTOS (DISSE QUE É O ANTIGO INQUILINO DO IMÓVEL): N/C | S63: =IF(F63<TODAY(),"EXECUTADA",IF(F63=TODAY(),"EM EXECUÇÃO",IF(F63=TODAY()+1,"VALIDAR HOJE",IF(F63>TODAY()+1,"VALIDAR DEPOIS","-")))) -> EXECUTADA
A64: MUD END ENEIAS RODRIGUES DE SOUZA (NOVO VISUAL SERVICOS GRAFICA) PROT:2603.1107 PIX (HALYSON) - OSVALDO REZENDE **(POSSUI WI-FI EXTEND)** | B64: MUD END | D64: JA VALIDADO ANTERIOMENTE POR MARCELLA CONEXÃO AINDA ESTÁ ATIVA NO ENDEREÇO ANTIGO | E64: 34992322706 | F64: 46121 | G64: =PROPER(TEXT(F64,"DDD")) -> Qui | H64: 0.33333333 | I64: PIX | J64: ENDEREÇO NOVO: RUA ANTÔNIO THOMAZ DE REZENDE, 201 COMPLEMENTO: SALA 5 REFERÊNCIA: GALPÃO CEP: 38400487 BAIRRO: OSVALDO REZENDE | K64: <b>ONT = ONT TP LINK 530 // CONECTOR = VERDE.</b> | L64: =IF(B64="MUD END","NÃO","SIM") -> NÃO | M64: - | N64: SIM | O64: - | P64: - | Q64: COMPROVANTE DE ENDEREÇO (NOTA FISCAL) EM ANEXO NOME NO COMPROVANTE: GRAFICA E EDITORA UNIAO PRINT LTDA (EMPRESA DO ASSINANTE) | R64: MK END: N/C MK NOMES - GRAFICA E EDITORA UNIAO PRINT LTDA 61.401.489/0001-06 (EMPRESA DO ASSINANTE): N/C - ENEIAS RODRIGUES DE SOUZA (NOVO VISUAL SERVICOS GRAFICA): POSSUI CONEXÃO ATIVA E ADIMPLENTE - JULIO GONCALVES JUNIOR (SOCIO DE GRAFICA E EDITORA UNIAO PRINT): PROCESSO DE ADESÃO CANCELADO POR PARTE DO CLIENTE, MOTIVO VENDEU A CASA EM 22/03/2023 - UNIPEL INDUSTRIAL E COMERCIAL LTDA 03.145.102/0001-93 (FORNECEDORA): N/C | S64: =IF(F64<TODAY(),"EXECUTADA",IF(F64=TODAY(),"EM EXECUÇÃO",IF(F64=TODAY()+1,"VALIDAR HOJE",IF(F64>TODAY()+1,"VALIDAR DEPOIS","-")))) -> EXECUTADA
A65: MUD END YARA CHRISTINA SILVA SANTOS PROT:2604.5304 CARTAO (LUIS) - PATRIMÔNIO **PRÉDIO COM PRUMADA** *PODE ANTECIPAR* | B65: MUD END | D65: VALIDAÇÃO OK ENVIAR AO CADASTRO | E65: 34997186698 | F65: 46121 | G65: =PROPER(TEXT(F65,"DDD")) -> Qui | H65: 0.33333333 | I65: CARTÃO | J65: ENDEREÇO NOVO: AVENIDA OSCARINA CUNHA CHAVES, 510 COMPLEMENTO: SPAZIO UNIGARDEN, BL 04 APT 106 CEP: 38411102 BAIRRO: PATRIMÔNIO | K65: <b>ONT = ONT TP LINK 530 // CONECTOR = VERDE.</b> | L65: =IF(B65="MUD END","NÃO","SIM") -> NÃO | M65: - | N65: SIM | O65: - | P65: - | Q65: COMPROVANTE DE ENDEREÇO (CEMIG) EM ANEXO NOME NO COMPROVANTE: YARA CHRISTINA SILVA SANTOS (ASSINANTE) | R65: MK END: N/C MK NOME: YARA CHRISTINA SILVA SANTOS - CPF 099.242.126-81 - ASSINANTE - CLIENTE ATIVO E ADIMPLENTE COM A EMPRESA. | S65: =IF(F65<TODAY(),"EXECUTADA",IF(F65=TODAY(),"EM EXECUÇÃO",IF(F65=TODAY()+1,"VALIDAR HOJE",IF(F65>TODAY()+1,"VALIDAR DEPOIS","-")))) -> EXECUTADA
A66: RESERVA - CARLOS EDUARDO GOMES SOARES / MUD / PRT PEDRO | B66: MUD END | D66: SEM OS GERADA SEM CONFERENCIAS MENSALIDADE PENDENTE ENDEREÇO NAO ALTERADO | E66: 34998331025 | F66: 46121 | G66: =PROPER(TEXT(F66,"DDD")) -> Qui | H66: 0.41666667 | I66: CARTÃO | J66: ENDEREÇO NOVO: RUA WEBERSON ARANTES, 402 COMPLEMENTO: CASA ÚNICA CEP: 38418676 BAIRRO: MANSOUR III | L66: =IF(B66="MUD END","NÃO","SIM") -> NÃO | Q66: COMPROVANTE DE ENDEREÇO (CEMIG) EM ANEXO NOME NO COMPROVANTE: FAUSTO FERNANDES DE OLIVEIRA (DISSE SER O ANTIGO MORADOR) | R66: FAUSTO FERNANDES DE OLIVEIRA - BAIXADO POR INADIMPLENCIA - EQUIPAMENTOS DEVOLVIDOS DÉBITO RESTANTE EM R$1.123,78 | S66: =IF(F66<TODAY(),"EXECUTADA",IF(F66=TODAY(),"EM EXECUÇÃO",IF(F66=TODAY()+1,"VALIDAR HOJE",IF(F66>TODAY()+1,"VALIDAR DEPOIS","-")))) -> EXECUTADA
A67: MUD END GABRIEL COSTA SCARPINS PROT:2604.2915 PIX (LUIS) - MORUMBI // *PODE ANTECIPAR* | B67: MUD END | D67: ENDEREÇO DIVERGENTE DO CONTRATO - FAVOR VERIFICAR | E67: 34998610701 | F67: 46121 | G67: =PROPER(TEXT(F67,"DDD")) -> Qui | H67: 0.41666667 | I67: PIX | J67: ENDEREÇO NOVO: RUA DA BOA VENTURA, 31 COMPLEMENTO: CASA ÚNICA CEP: 38407520 BAIRRO: RESIDENCIAL INTEGRAÇÃO | K67: <b>ONT = ONT TP LINK 230 // CONECTOR = VERDE.</b> | L67: =IF(B67="MUD END","NÃO","SIM") -> NÃO | M67: - | N67: SIM | O67: - | P67: - | Q67: COMPROVANTE DE ENDEREÇO (CONTRATO DE LOCAÇÃO) EM ANEXO NOME NO COMPROVANTE: GABRIEL COSTA SCARPINS (ASSINANTE) | R67: MK END: N/C MK NOMES: LOCADOR / PROPRIETÁRIO DO IMÓVEL GLEIDSON SANTOS RIBEIRO / CPF: 053.349.136-37 - N/C GABRIEL COSTA SCARPINS / CPF: 019.866.266-10 ASSINANTE, CONEXÃO ATIVA E ADIMPLENTE | S67: =IF(F67<TODAY(),"EXECUTADA",IF(F67=TODAY(),"EM EXECUÇÃO",IF(F67=TODAY()+1,"VALIDAR HOJE",IF(F67>TODAY()+1,"VALIDAR DEPOIS","-")))) -> EXECUTADA
A68: MUD END + ALT PLANO LUCELIA SANTOS PROT:2604.6684 ISENTO (VICTOR H.) - SEGISMUNDO PEREIRA // | B68: MUD END + ALT PLAN | D68: VALIDAÇÃO OK ENVIAR AO CADASTRO | E68: 34991214517 | F68: 46121 | G68: =PROPER(TEXT(F68,"DDD")) -> Qui | H68: 0.54166667 | I68: ISENTO | J68: ENDEREÇO NOVO: RUA JAMIL ABRÃO, 135 COMPLEMENTO: CASA FUNDO CEP: 38408306 BAIRRO: SEGISMUNDO PEREIRA | K68: <b>ONT = ONT TP LINK 230 // CONECTOR = VERDE.</b> | L68: =IF(B68="MUD END","NÃO","SIM") -> SIM | M68: PLANO ATUAL: 600 MEGA/79,90 CONTRATADO EM 07/2025 COM FIDELIDADE DE 12 MESES. ROTEADOR: ONT TP-LINK XC230 PLANO OFERTADO: 600 MEGA/79,90. BENEFÍCIOS: ACESSO GRATUITO AO APP MZTV (CDNTV+) | N68: SIM | O68: - | P68: - | Q68: COMPROVANTE DE ENDEREÇO (CEMIG) EM ANEXO NOME NO COMPROVANTE: MARIA DE LOURDES DOS SANTOS (MÃE DA ASSINANTE) | R68: MK NOME: MARIA DE LOURDES DOS SANTOS (MÃE DA ASSINANTE) N/C INICIO DO CPF DELA É 713.2 NÃO POSSUI O RESTANTE POIS PEGUEI DO TALÃO DA CEMIG EXISTE NA BASE OUTRA MARIA DE LOURDES DOS SANTOS CPF: 033.290.166-12 NÃO TEM VINCULO COM A ASSINANTE OU COMPROVANTE MK END: N/C | S68: =IF(F68<TODAY(),"EXECUTADA",IF(F68=TODAY(),"EM EXECUÇÃO",IF(F68=TODAY()+1,"VALIDAR HOJE",IF(F68>TODAY()+1,"VALIDAR DEPOIS","-")))) -> EXECUTADA
A69: MUD END ALEXANDRE HELVES MOREIRA (EQUIPE XANDE MOREIRA) PROT:2604.3388 CARTAO (RONALD) - LUIZOTE DE FREITAS | B69: MUD END | D69: PENDENTE MENSALIDADE CLIENTE SOLICITOU CANCELAMENTO | E69: 34991769543 | F69: 46121 | G69: =PROPER(TEXT(F69,"DDD")) -> Qui | H69: 0.54166667 | I69: CARTÃO | J69: ENDEREÇO NOVO: RUA AUGUSTO MACHADO, 60 COMPLEMENTO: COMERCIO CEP: 38414298 BAIRRO: LUIZOTE DE FREITAS | K69: <b>ONT = ONT TP LINK 220 // CONECTOR = VERDE.</b> | L69: =IF(B69="MUD END","NÃO","SIM") -> NÃO | M69: - | N69: SIM | O69: - | P69: - | Q69: COMPROVANTE DE ENDEREÇO (CEMIG) EM ANEXO NOME NO COMPROVANTE: THAIS KELEN BELAFONTE BIDOIA (PROPRIETARIA DO IMOVEL) | R69: MK END; N/C MK NOME; ALEXANDRE HELVES MOREIRA (EQUIPE XANDE MOREIRA) CONEXÃO ATIVA E CLIENTE ADIMPLENTE. THAIS KELEN BELAFONTE BIDOIA (PROPRIETARIA DO IMOVEL) N/C | S69: =IF(F69<TODAY(),"EXECUTADA",IF(F69=TODAY(),"EM EXECUÇÃO",IF(F69=TODAY()+1,"VALIDAR HOJE",IF(F69>TODAY()+1,"VALIDAR DEPOIS","-")))) -> EXECUTADA
A70: MUD END LEANDRO DE OLIVEIRA CAMARA PROT:2604.3162 PIX (ANDREZA) - DANIEL FONSECA **PRÉDIO COM PRUMADA** | B70: MUD END | D70: VALIDAÇÃO OK ENVIAR AO CADASTRO | E70: 34991893862 | F70: 46121 | G70: =PROPER(TEXT(F70,"DDD")) -> Qui | H70: 0.625 | I70: PIX | J70: ENDEREÇO NOVO: RUA VARGINHA, 1155 COMPLEMENTO: APTO 601 CEP: 38400322 BAIRRO: DANIEL FONSECA | K70: <b>ONT = ONT ZTE // CONECTOR = VERDE.</b> | L70: =IF(B70="MUD END","NÃO","SIM") -> NÃO | M70: - | N70: SIM | O70: - | P70: - | Q70: COMPROVANTE DE ENDEREÇO (CONTRATO DE LOCAÇÃO) EM ANEXO NOME NO COMPROVANTE: LEANDRO DE OLIVEIRA CAMARA (ASSINANTE) | R70: MK END: N/C __________________________________ MK NOMES: -> ANA JULIA BENICHIO ZAGO (LOCADORA) - CPF 067.714.616-70: N/C -> LEANDRO DE OLIVEIRA CAMARA (LOCATÁRIO) - CPF 105.914.476-06: ASSINANTE DA CONEXÃO. | S70: =IF(F70<TODAY(),"EXECUTADA",IF(F70=TODAY(),"EM EXECUÇÃO",IF(F70=TODAY()+1,"VALIDAR HOJE",IF(F70>TODAY()+1,"VALIDAR DEPOIS","-")))) -> EXECUTADA
A71: MUD END + ALT PLANO HALLINE ALVES CAVALCANTE PACHECO PROT:2603.34786 ISENTO (VITOR/JHONATAN) - JARDIM INCONFIDÊNCIA // | B71: MUD END + ALT PLAN | D71: VALIDAÇÃO OK ENVIAR AO CADASTRO | E71: 34991964879 | F71: 46121 | G71: =PROPER(TEXT(F71,"DDD")) -> Qui | H71: 0.625 | I71: ISENTO | J71: ENDEREÇO NOVO: ALAMEDA DOMINGOS DE ABREU VIEIRA, 62 COMPLEMENTO: CASA UNICA CEP: 38411266 BAIRRO: JARDIM INCONFIDÊNCIA | K71: . <b>ONT = ONT ZTE // CONECTOR = VERDE.</b> | L71: =IF(B71="MUD END","NÃO","SIM") -> SIM | M71: PLANO ATUAL: 600 MEGA/79,90 CONTRATADO EM 05/2025 COM FIDELIDADE DE 12 MESES. ROTEADOR: ONT ZTE F 670-L PLANO OFERTADO: 600 MEGA/79,90. BENEFÍCIOS: ACESSO GRATUITO AO APP MZTV (CDNTV+) | N71: SIM | O71: - | P71: - | Q71: COMPROVANTE DE ENDEREÇO (CEMIG) EM ANEXO NOME NO COMPROVANTE: VANDRE ARANTES MAGALHAES (DISSE QUE É O ESPOSO) | R71: MK END: N/C MK NOME: VANDRE ARANTES MAGALHAES (DISSE QUE É O ESPOSO): N/C | S71: =IF(F71<TODAY(),"EXECUTADA",IF(F71=TODAY(),"EM EXECUÇÃO",IF(F71=TODAY()+1,"VALIDAR HOJE",IF(F71>TODAY()+1,"VALIDAR DEPOIS","-")))) -> EXECUTADA
A72: MUD END CARLOS HAILTON MUNIZ FERREIRA PROT:2603.34987 DINHEIRO (RONALD) - MORUMBI | B72: MUD END | D72: PENDENTE MENSALIDADE | E72: 34996941853 | F72: 46121 | G72: =PROPER(TEXT(F72,"DDD")) -> Qui | H72: 0.70833333 | I72: DINHEIRO | J72: ENDEREÇO NOVO: RUA ARRUDA, 203 COMPLEMENTO: CASA ÚNICA CEP: 38407129 BAIRRO: MORUMBI | K72: <b>ONU = DATA // CONECTOR = VERDE.</b> | L72: =IF(B72="MUD END","NÃO","SIM") -> NÃO | M72: - | N72: SIM | O72: - | P72: - | Q72: COMPROVANTE DE ENDEREÇO (CEMIG) EM ANEXO NOME NO COMPROVANTE: MARIA APARECIDA DA SILVA (ANTIGA INQUILINA) | R72: MK END; JHOATAN JUNIO RODRIGUES LIMA SOLICITOU CONTRATAÇÃO EM 04/2025 PORÉM NÃO FOI APROVADO COM INSTALAÇÃO GRATUITA, PORÉM NÃO TEVE INTERESSE. MK NOME; CARLOS HAILTON MUNIZ FERREIRA (ASSINANTE) CONEXÃO ATIVA E CLIENTE ADIMPLENTE MARIA APARECIDA DA SILVA 366.4**.***-** (ANTIGA INQUILINA) N/C | S72: =IF(F72<TODAY(),"EXECUTADA",IF(F72=TODAY(),"EM EXECUÇÃO",IF(F72=TODAY()+1,"VALIDAR HOJE",IF(F72>TODAY()+1,"VALIDAR DEPOIS","-")))) -> EXECUTADA
A73: MUD END + ALT PLANO EMERSON SILVEIRA DA SILVA PROT:2604.5227 ISENTO (PEDRO) - JARDIM DAS PALMEIRAS // | B73: MUD END + ALT PLAN | D73: VALIDAÇÃO OK ENVIAR AO CADASTRO COBRAR ASSINATURA DO CONTRATO | E73: 34998726994 | F73: 46121 | G73: =PROPER(TEXT(F73,"DDD")) -> Qui | H73: 0.70833333 | I73: ISENTO | J73: ENDEREÇO NOVO: RUA DO POETA, 501 COMPLEMENTO: CASA ÚNICA CEP: 38412276 BAIRRO: JARDIM DAS PALMEIRAS | K73: <b>ONT = ONT TP LINK 530 // CONECTOR = VERDE.</b> | L73: =IF(B73="MUD END","NÃO","SIM") -> SIM | M73: PLANO ATUAL: 1000 MEGA/99,90 CONTRATADO EM 07/2025 COM FIDELIDADE DE 12 MESES. ROTEADOR: ONT TP-LINK X530 PLANO OFERTADO: 1 GIGA (1.000 MEGA) R$99,90. BENEFÍCIOS: ACESSO GRATUITO AO APP MZTV (CDNTV+) + VOD | N73: SIM | O73: - | P73: - | Q73: COMPROVANTE DE ENDEREÇO (DMAE) EM ANEXO NOME NO COMPROVANTE: ELZIO ANTUNES DE OLIVEIRA (DISSE SER O DONO DO IMÓVEL) | R73: MK END: N/C MK NOME: EMERSON SILVEIRA DA SILVA (TITULAR) - POSSUI CONEXÃO CONOSCO DESDE 09/2021, ATIVA E ADIMPLENTE. ELZIO ANTUNES DE OLIVEIRA (DISSE SER O DONO DO IMÓVEL) - N/C | S73: =IF(F73<TODAY(),"EXECUTADA",IF(F73=TODAY(),"EM EXECUÇÃO",IF(F73=TODAY()+1,"VALIDAR HOJE",IF(F73>TODAY()+1,"VALIDAR DEPOIS","-")))) -> EXECUTADA
A74: MUD END ALEXANDRE HELVES MOREIRA (EQUIPE XANDE MOREIRA) PROT:2604.3388 CARTAO (RONALD) - LUIZOTE DE FREITAS | B74: MUD END | D74: VALIDAÇÃO OK ENVIAR AO CADASTRO | E74: 34991769543 | F74: 46121 | G74: =PROPER(TEXT(F74,"DDD")) -> Qui | H74: 0.54166667 | I74: CARTÃO | J74: ENDEREÇO NOVO: RUA AUGUSTO MACHADO, 60 COMPLEMENTO: COMERCIO CEP: 38414298 BAIRRO: LUIZOTE DE FREITAS | K74: <b>ONT = ONT TP LINK 220 // CONECTOR = VERDE.</b> | L74: =IF(B74="MUD END","NÃO","SIM") -> NÃO | M74: - | N74: SIM | O74: - | P74: - | Q74: COMPROVANTE DE ENDEREÇO (CEMIG) EM ANEXO NOME NO COMPROVANTE: THAIS KELEN BELAFONTE BIDOIA (PROPRIETARIA DO IMOVEL) | R74: MK END; N/C MK NOME; ALEXANDRE HELVES MOREIRA (EQUIPE XANDE MOREIRA) CONEXÃO ATIVA E CLIENTE ADIMPLENTE. THAIS KELEN BELAFONTE BIDOIA (PROPRIETARIA DO IMOVEL) N/C | S74: =IF(F74<TODAY(),"EXECUTADA",IF(F74=TODAY(),"EM EXECUÇÃO",IF(F74=TODAY()+1,"VALIDAR HOJE",IF(F74>TODAY()+1,"VALIDAR DEPOIS","-")))) -> EXECUTADA
A75: MUD END + ALT PLANO RENATO ROSA DA SILVA PROT:2604.8547 ISENTO (PEDRO) - JARDIM CANAÃ // | B75: MUD END + ALT PLAN | D75: VALIDAÇÃO OK ENVIAR AO CADASTRO COBRAR ASSINATURA DO CONTRATO | E75: 34998363246 | F75: 46122 | G75: =PROPER(TEXT(F75,"DDD")) -> Sex | H75: 0.33333333 | I75: ISENTO | J75: ENDEREÇO NOVO: RUA TERCILIO RODRIGUES QUEIROZ, 660 COMPLEMENTO: CASA ÚNICA CEP: 38412487 BAIRRO: JARDIM CANAÃ | K75: <b>ONT = ONT TP LINK 230 // CONECTOR = VERDE.</b> | L75: =IF(B75="MUD END","NÃO","SIM") -> SIM | M75: PLANO ATUAL: 600 MEGA/79,90 CONTRATADO EM 06/2025 COM FIDELIDADE DE 12 MESES. ROTEADOR: ONT TP-LINK XC230 PLANO OFERTADO: 600 MEGA/79,90. BENEFÍCIOS: ACESSO GRATUITO AO APP MZTV (CDNTV+) | N75: SIM | O75: - | P75: - | Q75: COMPROVANTE DE ENDEREÇO (BOLETO DA ALGAR) EM ANEXO NOME NO COMPROVANTE: PAULO CESAR SEVERINO DE AZEVEDO (DISSE SER O DONO DA CASA) | R75: MK END: N/C MK NOME: PAULO CESAR SEVERINO DE AZEVEDO (DISSE SER O DONO DA CASA) - N/C RENATO ROSA DA SILVA (TITULAR) - POSSUI CONEXÃO CONOSCO DESDE 06/2025, ATIVA E ADIMPLENTE. | S75: =IF(F75<TODAY(),"EXECUTADA",IF(F75=TODAY(),"EM EXECUÇÃO",IF(F75=TODAY()+1,"VALIDAR HOJE",IF(F75>TODAY()+1,"VALIDAR DEPOIS","-")))) -> EXECUTADA
A76: MUD END CARLOS AUGUSTO RODRIGUES DE MATTOS PROT:2603.33782 CARTAO (GABRIEL M.) - LAGOINHA | | B76: MUD END | D76: mudança negada pelo cadastro .. elias (casa fundos) precisa quitar os débitos primeiro | F76: 46122 | G76: =PROPER(TEXT(F76,"DDD")) -> Sex | H76: 0.33333333 | I76: CARTÃO | L76: =IF(B76="MUD END","NÃO","SIM") -> NÃO | S76: =IF(F76<TODAY(),"EXECUTADA",IF(F76=TODAY(),"EM EXECUÇÃO",IF(F76=TODAY()+1,"VALIDAR HOJE",IF(F76>TODAY()+1,"VALIDAR DEPOIS","-")))) -> EXECUTADA
A77: MUD END MALIANE PEREIRA BATISTA PROT:2604.3813 PIX (PEDRO) - SÃO JORGE *PENDENTE COMPROVANTE* | B77: MUD END | D77: pendente comprovante de residencia endereço não alterado | E77: 34999772948 | F77: 46122 | G77: =PROPER(TEXT(F77,"DDD")) -> Sex | H77: 0.41666667 | I77: PIX | J77: ENDEREÇO NOVO: , 358 COMPLEMENTO: CASA ÚNICA CEP: 384100372 BAIRRO: | K77: <b>ONU = DATA // CONECTOR = VERDE.</b> | L77: =IF(B77="MUD END","NÃO","SIM") -> NÃO | M77: - | N77: SIM | O77: - | P77: - | Q77: PENDENTE | S77: =IF(F77<TODAY(),"EXECUTADA",IF(F77=TODAY(),"EM EXECUÇÃO",IF(F77=TODAY()+1,"VALIDAR HOJE",IF(F77>TODAY()+1,"VALIDAR DEPOIS","-")))) -> EXECUTADA
A78: MUD END ANGELICA OLIVEIRA DA SILVA PROT:2604.4813 PIX (RAMONY) - SANTA ROSA | B78: MUD END | D78: VALIDAÇÃO OK ENVIAR AO CADASTRO | E78: 34996715311 | F78: 46122 | G78: =PROPER(TEXT(F78,"DDD")) -> Sex | H78: 0.41666667 | I78: PIX | J78: ENDEREÇO NOVO: AVENIDA ANÁLIA RESENDE SIQUIEROLI, 2590 COMPLEMENTO: CASA FUNDOS CEP: 38401799 BAIRRO: SANTA ROSA | K78: <b>ONT = ONT TP LINK 530 // CONECTOR = VERDE.</b> | L78: =IF(B78="MUD END","NÃO","SIM") -> NÃO | M78: - | N78: SIM | O78: - | P78: - | Q78: COMPROVANTE DE ENDEREÇO (CONTRATO DE LOCAÇÃO) EM ANEXO NOME NO COMPROVANTE: LARISSA DA COSTA SILVA OLIVEIRA (ENTEADA) | R78: MK END: N/C MK NOMES: > LOCADOR: ESPÓLIO DE ONOFRE LUIZ BORGES - N/C CPF: 212.406.806-78 > REPRESENTANTES DO LOCADOR / ADMINISTRADORES CITYVAL CONSULTORIA DE IMÓVEIS LTDA - N/C CNPJ: 41.756.289/0001-50 VALDO JACINTO DE SOUSA - N/C CPF: 167.691.121-91 > LOCATÁRIOS: LARISSA DA COSTA SILVA OLIVEIRA - N/C CPF: 703.262.106-60 (ENTEADA DA TITULAR) ANGELICA OLIVEIRA DA SILVA CPF: 109.523.266-55 (TITULAR DA CONEXÃO - ATIVO E ADIMPLENTE) > TESTEMUNHAS: ANACLEIA DA COSTA NASCIMENTO - N/C CPF: 047.045.236-67 SOLAINE M. C. LEOPOLDINO - N/C CPF: 030.870.906-38 | S78: =IF(F78<TODAY(),"EXECUTADA",IF(F78=TODAY(),"EM EXECUÇÃO",IF(F78=TODAY()+1,"VALIDAR HOJE",IF(F78>TODAY()+1,"VALIDAR DEPOIS","-")))) -> EXECUTADA
A79: MUD END + ALT PLANO JANETE LOPES SOARES PROT:2604.4617 ISENTO (GABRIEL M.) - GRANADA **PRÉDIO SEM PRUMADA *PODE ANTECIPAR* | B79: MUD END + ALT PLAN | D79: VALIDAÇÃO OK ENVIAR AO CADASTRO COBRAR ASSINATURA DO CONTRATO | E79: 34991178783 | F79: 46122 | G79: =PROPER(TEXT(F79,"DDD")) -> Sex | H79: 0.54166667 | I79: ISENTO | J79: ENDEREÇO NOVO: RUA BOA ESPERANÇA, 200 COMPLEMENTO: APTO. 101 CEP: 38410554 BAIRRO: GRANADA | K79: <b>ONT = ONT TP LINK 230 // CONECTOR = VERDE.</b> | L79: =IF(B79="MUD END","NÃO","SIM") -> SIM | M79: PLANO ATUAL: 600 MEGA/79,90 CONTRATADO EM 01/2025 COM FIDELIDADE DE 12 MESES. ROTEADOR: ONT TP-LINK XC230 PLANO OFERTADO: 600 MEGA/79,90. BENEFÍCIOS: ACESSO GRATUITO AO APP MZTV (CDNTV+) | N79: SIM | O79: - | P79: - | Q79: COMPROVANTE DE ENDEREÇO (DMAE) EM ANEXO NOME NO COMPROVANTE: ESTEIO EMPREENDIMENTOS IMOBILIARIOS LTDA (ANTIGO PROPRIETÁRIO) | R79: MK END: N/C MK NOMES: ESTEIO EMPREENDIMENTOS IMOBILIARIOS LTDA: N/C | S79: =IF(F79<TODAY(),"EXECUTADA",IF(F79=TODAY(),"EM EXECUÇÃO",IF(F79=TODAY()+1,"VALIDAR HOJE",IF(F79>TODAY()+1,"VALIDAR DEPOIS","-")))) -> EXECUTADA
A80: MUD END JULIANE CARAVIERI MARTINS PROT:2604.6196 CARTAO (ANDREZA) - OSVALDO REZENDE **PRÉDIO SEM PRUMADA** | B80: MUD END | D80: VALIDAÇÃO OK ENVIAR AO CADASTRO | E80: 34992048787 | F80: 46122 | G80: =PROPER(TEXT(F80,"DDD")) -> Sex | H80: 0.54166667 | I80: CARTÃO | J80: ENDEREÇO NOVO: AVENIDA ESTRÊLA DO SUL, 2015 COMPLEMENTO: APTO 101 CEP: 38400389 BAIRRO: OSVALDO REZENDE | K80: <b>ONT = ONT TP LINK 220 // CONECTOR = VERDE.</b> | L80: =IF(B80="MUD END","NÃO","SIM") -> NÃO | M80: - | N80: SIM | O80: - | P80: - | Q80: COMPROVANTE DE ENDEREÇO (CONTRATO DE LOCAÇÃO) EM ANEXO NOME NO COMPROVANTE: JULIANE CARAVIERI MARTINS (ASSINANTE) | R80: MK END: N/C ________________________________________ MK NOMES: -> RODRIGO RIBEIRO DOS SANTOS (PROPRIETÁRIO) - CPF 907.023.441-68: N/C -> SPINI IMOVEIS E ADMINISTRADORA DE ALUGUEIS LTDA (EMPRESA REPRESENTANTE) - CNPJ 26.725.593/0001-47: N/C -> LUIZ HUMBERTO SPINI NETO (REPRESENTANTE) - CPF 068.867.266-33: N/C -> JULIANE CARAVIERI MARTINS (LOCATÁRIA) - CPF 159.299.258-79: ASSINANTE DA CONEXÃO. -> ILZA MARIA DE ATAIDES (FIADORA) - CPF 060.441.071-91: N/C -> ADRIANA ALBANO (TESTEMUNHA) - CPF 158.506.468-84: N/C -> DANIELLA ALVES DE FREITAS (TESTEMUNHA) - CPF 070.331.676-10: N/C | S80: =IF(F80<TODAY(),"EXECUTADA",IF(F80=TODAY(),"EM EXECUÇÃO",IF(F80=TODAY()+1,"VALIDAR HOJE",IF(F80>TODAY()+1,"VALIDAR DEPOIS","-")))) -> EXECUTADA
A81: RESERVA ANDREZA - GEOVANNA FERNANDES SILVA | B81: MUD END | D81: SEM PROTOCOLO E OS REMOVIDO AGENDAMENTO | E81: 34999684184 | F81: 46122 | G81: =PROPER(TEXT(F81,"DDD")) -> Sex | H81: 0.625 | L81: =IF(B81="MUD END","NÃO","SIM") -> NÃO | S81: =IF(F81<TODAY(),"EXECUTADA",IF(F81=TODAY(),"EM EXECUÇÃO",IF(F81=TODAY()+1,"VALIDAR HOJE",IF(F81>TODAY()+1,"VALIDAR DEPOIS","-")))) -> EXECUTADA
A82: MUD END FABIO NEY ANDRADE DA SILVA PROT:2604.4451 PIX (JHONATAN) - TAIAMAN | B82: MUD END | D82: VALIDAÇÃO OK ENVIAR AO CADASTRO | E82: 34999314268 | F82: 46122 | G82: =PROPER(TEXT(F82,"DDD")) -> Sex | H82: 0.70833333 | I82: PIX | J82: ENDEREÇO NOVO: RUA DOS CLARINETES, 87 COMPLEMENTO: CASA 2 CEP: 38415078 BAIRRO: TAIAMAN | K82: <b>ONT = ONT TP LINK 530 // CONECTOR = VERDE.</b> | L82: =IF(B82="MUD END","NÃO","SIM") -> NÃO | M82: - | N82: SIM | O82: - | P82: - | Q82: COMPROVANTE DE ENDEREÇO (CEMIG) EM ANEXO NOME NO COMPROVANTE: ADIVANIA GALDINO (ANTIGA INQUILINA) | R82: MK END: -> IGOR ANTONIO DA SILVA PEDROZA - PROPOSTA RECUSADA EM 09/2020 -> HD EMPREENDIMENTOS EIRELI - CONEXEÇÃO CANCELADA EM 03/2022 - SEM DÉBITOS E EQUIPAMENTOS DEVOLVIDOS -> ADIVANIA GALDINO - CONEXEÇÃO CANCELADA EM 05/2023 - SEM DÉBITOS E EQUIPAMENTOS DEVOLVIDOS -> ALESSANDRA PEREIRA DE OLIVEIRA - APENAS LEAD MK NOMES: -> ADIVANIA GALDINO (ANTIGA INQUILINA): * ADIVANIA GALDINO - CONEXEÇÃO CANCELADA EM 05/2023 - SEM DÉBITOS E EQUIPAMENTOS DEVOLVIDOS ** ADIVANIA GALDINO (CASA DANIELA - FILHA) - CONEXÃO ATIVA E ADIMPLENTE | S82: =IF(F82<TODAY(),"EXECUTADA",IF(F82=TODAY(),"EM EXECUÇÃO",IF(F82=TODAY()+1,"VALIDAR HOJE",IF(F82>TODAY()+1,"VALIDAR DEPOIS","-")))) -> EXECUTADA
A83: MUD END + ALT PLANO RAFAELA VITORIA SILVA MACEDO PROT:2604.6682 ISENTO (JHONATAN) - SANTA MÔNICA // | B83: MUD END + ALT PLAN | D83: VALIDAÇÃO OK ENVIAR AO CADASTRO | E83: 34997337294 | F83: 46122 | G83: =PROPER(TEXT(F83,"DDD")) -> Sex | H83: 0.70833333 | I83: ISENTO | J83: ENDEREÇO NOVO: RUA JOÃO PEREIRA DA SILVA, 334 COMPLEMENTO: APTO 303 CEP: 38408198 BAIRRO: SANTA MÔNICA | K83: <b>ONT = ONT TP LINK 220 // CONECTOR = VERDE.</b> | L83: =IF(B83="MUD END","NÃO","SIM") -> SIM | M83: PLANO ATUAL: 300 MEGA/69,90 CONTRATADO EM 08/2024 COM FIDELIDADE DE 12 MESES. ROTEADOR: ONT TP-LINK XC220 PLANO OFERTADO: 300 MEGA/69,90. BENEFÍCIOS: ACESSO GRATUITO AO APP MZTV (CDNTV+) | N83: SIM | O83: - | P83: - | R83: MK END: -> N/C MK NOME: -> RAFAELA VITORIA SILVA MACEDO (LOCATÁRIA): ASSINANTE DA CONEXÃO -> FÁTIMA TRENTIN PICOLI (LOCADORA): N/C -> MARIA APARECIDA DA SILVA MACEDO (FIADORA): N/C -> JEOVERSO BATISTA DE MACEDO (FIADOR): N/C * IMOBILIÁRIA -> IVAN NEGÓCIOS IMOBILIÁRIOS LTDA (ADMINISTRADORA): N/C -> IVAN GRACIANO DA COSTA FILHO (REPRESENTANTE): N/C -> RICARDO GRACIANO DA COSTA (REPRESENTANTE): N/C -> VICENTE PAULO FERREIRA (REPRESENTANTE): N/C -> JOYCE APARECIDA DIAS (REPRESENTANTE): N/C -> TAIZ LAMARA BALESTERE TEIXEIRA ALVES (REPRESENTANTE): N/C | S83: =IF(F83<TODAY(),"EXECUTADA",IF(F83=TODAY(),"EM EXECUÇÃO",IF(F83=TODAY()+1,"VALIDAR HOJE",IF(F83>TODAY()+1,"VALIDAR DEPOIS","-")))) -> EXECUTADA
A84: MUD END PAULA GIULLYANE S. F. (FAGUNDES E VEDRAMINE ADVOCACIA) PROT:2604.11096 PIX (ANDREZA) - PRESIDENTE ROOSEVELT **PRÉDIO SEM PRUMADA - ENVIAR TÉCNICO DUPLADO** // *14:00* | B84: MUD END | D84: SOLICITAÇÃO FEITA PELO CADASTRO VALIDAÇÃO OK | E84: 34996887707 | F84: 46122 | G84: =PROPER(TEXT(F84,"DDD")) -> Sex | H84: 0.58333333 | I84: PIX | J84: ENDEREÇO NOVO: RUA RODRIGO PEREIRA JÚNIOR, 700 COMPLEMENTO: APTO 303 CEP: 38401018 BAIRRO: PRESIDENTE ROOSEVELT | K84: <b>ONT = ONT TP LINK 530 // CONECTOR = VERDE.</b> | L84: =IF(B84="MUD END","NÃO","SIM") -> NÃO | M84: - | N84: NÃO | O84: CINTIA COSTA RESENDE (IRMÃ) | P84: 34 99186-8163 | Q84: COMPROVANTE DE ENDEREÇO (CONTRATO DE LOCAÇÃO) EM ANEXO NOME NO COMPROVANTE: ELTON PEREIRA DE RESENDE (DISSE QUE É O PAI DA CINTIA) | R84: MK END: -> PAULA GIULLYANE SILVA FAGUNDES (NOVA SOLICITACAO): SOLICITAÇÃO DE ADESÃO EM 04/2026 REPROVADA. ________________________________________ MK NOMES: -> CINTIA COSTA RESENDE (IRMÃ DA ASSINANTE): N/C -> BRAZ JOSE COUTINHO (LOCADOR) - CPF 206.624.246-20: N/C -> ISAIAS JUNIO COUTINHO (PROCURADOR) - CPF 033.157.826-36: N/C -> ELTON PEREIRA DE RESENDE (DISSE QUE É O PAI DA CINTIA/LOCATÁRIO) - CPF 210.440.076-72: N/C -> CATIA DALILA DE SOUSA RESENDE (LOCATÁRIA) - CPF 211.477.606-91: N/C | S84: =IF(F84<TODAY(),"EXECUTADA",IF(F84=TODAY(),"EM EXECUÇÃO",IF(F84=TODAY()+1,"VALIDAR HOJE",IF(F84>TODAY()+1,"VALIDAR DEPOIS","-")))) -> EXECUTADA
A85: MUD END + ALT PLANO THAMIRIS ALVES FARIA DE LEVA (AGRO LEVA) PROT:XXXXXX ISENTO (HALYSON) - JARDIM BRASÍLIA // | B85: MUD END + ALT PLAN | D85: VALIDAÇÃO OK ENVIAR AO CADASTRO | E85: 34996749996 | F85: 46123 | G85: =PROPER(TEXT(F85,"DDD")) -> Sáb | H85: 0.33333333 | I85: ISENTO | J85: ENDEREÇO NOVO: AVENIDA CONSTELAÇÃO, 791 COMPLEMENTO: LOJA CEP: 38401478 BAIRRO: JARDIM BRASÍLIA | K85: <b>ONT = ONT TP LINK 220 // CONECTOR = VERDE.</b> | L85: =IF(B85="MUD END","NÃO","SIM") -> SIM | M85: PLANO ATUAL: 500 MEGA/79,90 CONTRATADO EM 02/2024 COM FIDELIDADE DE 12 MESES. ROTEADOR: ONT TP-LINK XC220 PLANO OFERTADO: 600 MEGA/79,90. BENEFÍCIOS: ACESSO GRATUITO AO APP MZTV (CDNTV+) | N85: SIM | O85: - | P85: - | Q85: COMPROVANTE DE ENDEREÇO (CEMIG) EM ANEXO NOME NO COMPROVANTE: TINTAS UBERLANDIA LTDA (ANTIGO LOCATÁRIO) | R85: - MK END: EDSON FERNANDES LIDOGARIO DA SILVA (CENTRO DE TREINAMENTO TEAM BAIANO): POSSUI CONEXÃO ATIVA E ADIMPLENTE MK NOMES - THAMIRIS ALVES FARIA DE LEVA (AGRO LEVA) (ASSINANTE): POSSUI CONEXÃO ATIVA E ADIMPLENTE - THAMIRIS ALVES FARIA DE LEVA (089.869.586-43): POSSUI CONEXÃO ATIVA E ADIMPLENTE NO ENDEREÇO CRUZEIRO DO SUL Nº 41 AP 02- TERREO - JARDIM BRASILIA - THAMIRIS ALVES FARIA DE LEVA (D LEVA COOKIES) (26.057.341/0001-97): CONEXÃO CANCELADA SEM DÉBITOS - ANA CAROLINA MARCELINO ALVES 043.816.806-26 (SOCIA DA ASSINANTE): N/C - AGROLEVA CONSULTORIO VETERINARIO LTDA (EMPRESA): N/C ATUALIZAÇÃO MK NOMES - TINTAS UBERLANDIA LTDA (ANTIGO LOCATÁRIO): N/CARACT( | S85: =IF(F85<TODAY(),"EXECUTADA",IF(F85=TODAY(),"EM EXECUÇÃO",IF(F85=TODAY()+1,"VALIDAR HOJE",IF(F85>TODAY()+1,"VALIDAR DEPOIS","-")))) -> EXECUTADA
A86: MUD END MARISA RODRIGUES DOS SANTOS ROSA PROT:2604.5261 PIX (PEDRO) - SANTA MÔNICA **PRÉDIO SEM PRUMADA - ENVIAR TÉCNICO DUPLADO** | B86: MUD END | D86: VALIDAÇÃO OK ENVIAR AO CADASTRO | E86: 34991713655 | F86: 46123 | G86: =PROPER(TEXT(F86,"DDD")) -> Sáb | H86: 0.33333333 | I86: PIX | J86: ENDEREÇO NOVO: RUA PROFESSORA MARIA ALVES CASTILHO, 1019 COMPLEMENTO: RESIDENCIAL VANCOUVER, AP.301 CEP: 38408260 BAIRRO: SANTA MÔNICA | K86: <b>ONU = DATA // CONECTOR = VERDE.</b> | L86: =IF(B86="MUD END","NÃO","SIM") -> NÃO | M86: - | N86: NÃO | O86: IZABELLA (FILHA DE MARISA) | P86: (34) 99171-3655 | Q86: COMPROVANTE DE ENDEREÇO (TAXA DE MUDANÇA) EM ANEXO. NOME NO COMPROVANTE: GERCINO DE SOUZA E SILVA NETO (DISSE SER O DONO DO APARTAMENTO) | R86: MK END: N/C MK NOME: GERCINO DE SOUZA E SILVA NETO (PAGADOR / DISSE SER O DONO DO APARTAMENTO) - N/C GABRIELA AMANDA DA SILVA ROCHA (PAGADORA / DISSE SER UMA AMIGA QUE IRÁ DIVIDIR O AP.) - N/C MARISA RODRIGUES DOS SANTOS ROSA (TITULAR) - POSSUI CONEXÃO CONOSCO DESDE 10/2025, ATIVA E ADIMPLENTE, IZABELLA RODRIGUES SANTOS DE MIRANDA (FILHA DA TITULAR) - SOLCIITOU INSTALAÇÃO EM 10/2025, MAS FOI APROVADO PARA A MÃE. | S86: =IF(F86<TODAY(),"EXECUTADA",IF(F86=TODAY(),"EM EXECUÇÃO",IF(F86=TODAY()+1,"VALIDAR HOJE",IF(F86>TODAY()+1,"VALIDAR DEPOIS","-")))) -> EXECUTADA
A87: MUD END GIANN MARCO CAMPOS CEKOTA PROT:2604.6683 CARTAO (HALYSON) - GRAND VILLE **PRÉDIO COM PRUMADA** *ANÁLISE 90 DIAS* | B87: MUD END | D87: VALIDAÇÃO OK ENVIAR AO CADASTRO | E87: 34999909998 | F87: 46123 | G87: =PROPER(TEXT(F87,"DDD")) -> Sáb | H87: 0.33333333 | I87: CARTÃO | J87: ENDEREÇO NOVO: ALAMEDA DOS MANDARINS, 200 COMPLEMENTO: BLOCO 6 APTO 105 CEP: 38407661 BAIRRO: GRAND VILLE | K87: <b>ONU = DATA // CONECTOR = VERDE.</b> | L87: =IF(B87="MUD END","NÃO","SIM") -> NÃO | M87: - | N87: SIM | O87: - | P87: - | Q87: COMPROVANTE DE ENDEREÇO (CONTRATO DE LOCAÇÃO) EM ANEXO NOME NO COMPROVANTE: MILENA CAROLINA CEKOTA OCHOA (MÃE ASSINANTE) | R87: MK END: N/C MK NOMES: - GIANN MARCO CAMPOS CEKOTA (ASSINANTE): POSSUI CONEXÃO ATIVA E ADIMPLENTE - SCHWARTZ COBRE LTDA (BENEFICIÁRIA DO COMPROVANTE): N/C MK NOMES - DANILO RODRIGUES DA SILVA – CPF: 098.777.696-70 (LOCADOR): N/C - ARANTES NEGÓCIOS IMOBILIÁRIOS LTDA – CNPJ: 11.016.333/0001-25 – ADMINISTRADORA: N/C - ARANTES SOLUCOES IMOBILIARIAS LTDA – CNPJ: 48.825.741/0001-38 – ADMINISTRADORA: N/C - MILENA CAROLINA CEKOTA OCHOA – CPF: 711.636.332-75 – LOCATÁRIO(A): POSSUI PROCESSO DE ADESÃO EM ANDAMENTO - SUELEN AZEVEDO DOS REIS CEKOTA – CPF: 066.703.976-74 – FIADOR(A): N/C - GIANN MARCO CAMPOS CEKOTA - CPF 711.059.932-99 (ASSINANTE): POSSUI CONEXÃO ATIVA E ADIMPLENTE | S87: =IF(F87<TODAY(),"EXECUTADA",IF(F87=TODAY(),"EM EXECUÇÃO",IF(F87=TODAY()+1,"VALIDAR HOJE",IF(F87>TODAY()+1,"VALIDAR DEPOIS","-")))) -> EXECUTADA
A88: MUD END + ALT PLANO JESSICA SANTOS VENTURA PROT:2604.6577 ISENTO (JHONATAN) - JARDIM PATRÍCIA // *FATURA EM ABERTO* | B88: MUD END + ALT PLAN | D88: VALIDAÇÃO OK ENVIAR AO CADASTRO | E88: 34997075457 | F88: 46123 | G88: =PROPER(TEXT(F88,"DDD")) -> Sáb | H88: 0.41666667 | I88: ISENTO | J88: ENDEREÇO NOVO: RUA YOVETTE FONSECA MIGLIORINI, 140 COMPLEMENTO: CASA UNICA CEP: 38414175 BAIRRO: JARDIM PATRÍCIA | K88: <b>ONU = DATA // CONECTOR = VERDE.</b> | L88: =IF(B88="MUD END","NÃO","SIM") -> SIM | M88: PLANO ATUAL: 600 MEGA/79,90 CONTRATADO EM 11/2024 COM FIDELIDADE DE 12 MESES. ROTEADOR: ZTE H199-A PLANO OFERTADO: 600 MEGA/79,90. BENEFÍCIOS: ACESSO GRATUITO AO APP MZTV (CDNTV+) | N88: SIM | O88: - | P88: - | Q88: COMPROVANTE DE ENDEREÇO (CEMIG) EM ANEXO NOME NO COMPROVANTE: ELIVANIA GONCALVES SILVA (DISSE QUE É A ANTIGA INQUILINA) | R88: MK END: -> N/C MK NOME: -> ELIVANIA GONCALVES SILVA (DISSE QUE É A ANTIGA INQUILINA): N/C -> JESSICA SANTOS VENTURA (NOVA SOLICITACAO): PROPOSTA DE NOVA CONEXÃO RECUSADA 11/2024 | S88: =IF(F88<TODAY(),"EXECUTADA",IF(F88=TODAY(),"EM EXECUÇÃO",IF(F88=TODAY()+1,"VALIDAR HOJE",IF(F88>TODAY()+1,"VALIDAR DEPOIS","-")))) -> EXECUTADA
A89: resera ronald / mud end / GEOVANA EVELLYN FERREIRA | B89: MUD END + ALT PLAN | D89: VALIDAÇÃO OK ENVIAR AO CADASTRO | E89: 34988773864 | F89: 46123 | G89: =PROPER(TEXT(F89,"DDD")) -> Sáb | H89: 0.41666667 | I89: ISENTO | J89: ENDEREÇO NOVO: AVENIDA ÁFRICA, 1170 COMPLEMENTO: CASA TÉRREO CEP: 38405096 BAIRRO: TIBERY | K89: <b>ONT = ONT TP LINK 230 // CONECTOR = VERDE.</b> | L89: =IF(B89="MUD END","NÃO","SIM") -> SIM | M89: PLANO ATUAL: 600 MEGA/79,90 CONTRATADO EM 04/2025 COM FIDELIDADE DE 12 MESES. ROTEADOR: ONT TP-LINK XC230 PLANO OFERTADO: 600 MEGA/79,90. BENEFÍCIOS: ACESSO GRATUITO AO APP MZTV (CDNTV+) | N89: SIM | O89: - | P89: - | Q89: COMPROVANTE DE ENDEREÇO (CEMIG) EM ANEXO NOME NO COMPROVANTE: FRANCISCO PEREIRA DA SILVA (PROPRIETARIO/LOCADOR) | R89: MK END; N/C MK NOME; GEOVANA EVELLYN FERREIRA 148.689.866-19 (ASSINANTE) CONEXÃO ATIVA E ADIMPLENTE FRANCISCO PEREIRA DA SILVA 254.9**.***-** (PROPRIETARIO/LOCADOR) N/C | S89: =IF(F89<TODAY(),"EXECUTADA",IF(F89=TODAY(),"EM EXECUÇÃO",IF(F89=TODAY()+1,"VALIDAR HOJE",IF(F89>TODAY()+1,"VALIDAR DEPOIS","-")))) -> EXECUTADA
A90: MUD END MARIA LUIZA SILVA OLIVEIRA PROT:2603.11237 PIX (ANDREZA) - LARANJEIRAS | B90: MUD END | D90: VALIDAÇÃO OK ENVIAR AO CADASTRO | E90: 34997682445 | F90: 46123 | G90: =PROPER(TEXT(F90,"DDD")) -> Sáb | H90: APÓS AS 11:00 | I90: PIX | J90: ENDEREÇO NOVO: AVENIDA VEREADOR CARLITO CORDEIRO, 1855 COMPLEMENTO: RESERVA BARCELONA - BLOCO A, APTO 406 CEP: 38410733 BAIRRO: LARANJEIRAS | K90: <b>ONT = ONT TP LINK 220 // CONECTOR = VERDE.</b> | L90: =IF(B90="MUD END","NÃO","SIM") -> NÃO | M90: - | N90: SIM | O90: - | P90: - | Q90: COMPROVANTE DE ENDEREÇO (IPTU) EM ANEXO NOME NO COMPROVANTE: MURILO ALVES PASSOS (DISSE QUE É O DONO DO IMÓVEL) | R90: MK END: N/C ________________________________________ MK NOMES: -> MURILO ALVES PASSOS (DISSE QUE É O DONO DO IMÓVEL): N/C | S90: =IF(F90<TODAY(),"EXECUTADA",IF(F90=TODAY(),"EM EXECUÇÃO",IF(F90=TODAY()+1,"VALIDAR HOJE",IF(F90>TODAY()+1,"VALIDAR DEPOIS","-")))) -> EXECUTADA
A91: MUD END + ALT PLANO MATHEUS MARCO CASSIANO DE OLIVEIRA PROT:2604.4228 ISENTO (BRUNA) - NOVO MUNDO **PRÉDIO COM PRUMADA** // | B91: MUD END + ALT PLAN | D91: NECESSÁRIO ENVIO DA 2ª PAGINA DO CONTRATO DE COMPRA E VENDA, ONDE CONTÉM ENDEREÇO E DADOS DO IMÓVEL . OS ERRADA, NECESSÁRIO TROCA DE EQUIPAMENTOS. | E91: 11934320654 | F91: 46123 | G91: =PROPER(TEXT(F91,"DDD")) -> Sáb | H91: APÓS AS 11:00 | I91: ISENTO | J91: ENDEREÇO NOVO: RUA ALFREDO BOSI, 242 COMPLEMENTO: BL 2 AP 708 CEP: 38409120 BAIRRO: NOVO MUNDO | K91: <b>ONT = ONT TP LINK 220 // CONECTOR = VERDE.</b> | L91: =IF(B91="MUD END","NÃO","SIM") -> SIM | M91: PLANO ATUAL: 300 MEGA/69,90 CONTRATADO EM 04/25 COM FIDELIDADE DE 12 MESES. ROTEADOR: ONT TP-LINK XC220 PLANO OFERTADO: 1 GIGA (1.000 MEGA) R$99,90. BENEFÍCIOS: ACESSO GRATUITO AO APP MZTV (CDNTV+) + VOD | N91: SIM | O91: - | P91: - | Q91: COMPROVANTE DE ENDEREÇO (CONTRATO DE COMPRA E VENDA) EM ANEXO NOME NO COMPROVANTE: MATHEUS MARCO CASSIANO DE OLIVEIRA (ASSINANTE) | R91: MK END: N/C MK NOMES: MATEUS MARCO CASSIANO DE OLIVEIRA (ASSINANTE/COMPRADOR DO IMÓVEL): CONEXÃO ATIVA E SEM PENDENCIAS. OPÇÃO EMPREENDIMENTOS IMOBILIÁRIOS LTDA (PROMITENTE VENDEDORA): POSSUI 2 CONEXÃO ATIVAS, SEM PENDENCIAS. PAULO NAVES CAMARGO (SÓCIO ADMINISTRADOR DA EMPRESA OPÇÃO EMPREENDIMENTOS IMOBILIÁRIOS LTDA):N/C ECCOS BLACK NEGOCIOS IMOBILIARIOS LTDA (EMPRESA RESPONSÁVEL PELA INTERMEDIAÇÃO DO NEGÓCIO IMOBILIÁRIO):N/C | S91: =IF(F91<TODAY(),"EXECUTADA",IF(F91=TODAY(),"EM EXECUÇÃO",IF(F91=TODAY()+1,"VALIDAR HOJE",IF(F91>TODAY()+1,"VALIDAR DEPOIS","-")))) -> EXECUTADA
A92: MUD END VIVIANE DAVI RAMOS PROT:2604.6855 PIX (LUIS) - SANTA MÔNICA *PENDENTE COMPROVANTE DE ENDEREÇO* | B92: MUD END | D92: VALIDAÇÃO OK ENVIAR AO CADASTRO | E92: 34993230827 | F92: 46123 | G92: =PROPER(TEXT(F92,"DDD")) -> Sáb | H92: APÓS AS 11:00 | I92: PIX | J92: ENDEREÇO: RUA IZAU RANGEL DE MENDONÇA, 567 COMPLEMENTO:APT 301 BL A CEP: 38408-136 BAIRRO: SANTA MÔNICA | K92: <b>ONT = ONT TP LINK 530 // CONECTOR = VERDE.</b> | L92: =IF(B92="MUD END","NÃO","SIM") -> NÃO | M92: - | N92: SIM | O92: - | P92: - | Q92: PENDENTE COMPROVANTE | S92: =IF(F92<TODAY(),"EXECUTADA",IF(F92=TODAY(),"EM EXECUÇÃO",IF(F92=TODAY()+1,"VALIDAR HOJE",IF(F92>TODAY()+1,"VALIDAR DEPOIS","-")))) -> EXECUTADA
A93: MUD END EDILENE PEREIRA DOS SANTOS PROT:2604.7759 PIX (JHONATAN) - CUSTÓDIO PEREIRA *PODE ANTECIPAR* | B93: MUD END | D93: KAROLAYNE | F93: 46125 | G93: =PROPER(TEXT(F93,"DDD")) -> Seg | H93: 0.33333333 | L93: =IF(B93="MUD END","NÃO","SIM") -> NÃO | S93: =IF(F93<TODAY(),"EXECUTADA",IF(F93=TODAY(),"EM EXECUÇÃO",IF(F93=TODAY()+1,"VALIDAR HOJE",IF(F93>TODAY()+1,"VALIDAR DEPOIS","-")))) -> EXECUTADA
A94: MUD END FRANCIENE SILVA E SOUZA PROT:2604.8284 CARTAO (VICTOR H.) - LOTEAMENTO RESIDENCIAL PEQUIS *PODE ANTECIPAR* | B94: MUD END | D94: KAROLAYNE | F94: 46125 | G94: =PROPER(TEXT(F94,"DDD")) -> Seg | H94: 0.33333333 | L94: =IF(B94="MUD END","NÃO","SIM") -> NÃO | S94: =IF(F94<TODAY(),"EXECUTADA",IF(F94=TODAY(),"EM EXECUÇÃO",IF(F94=TODAY()+1,"VALIDAR HOJE",IF(F94>TODAY()+1,"VALIDAR DEPOIS","-")))) -> EXECUTADA
A95: MUD END LEANDRO DOS SANTOS SILVA PROT:2604.4921 CARTAO (JOSÉ Jr) - CUSTÓDIO PEREIRA | B95: MUD END | D95: AGENDA ESTÁ AS 10:00, PROTOCOLO ESTÁ AS 15:00 OS INCORRETA - CLIENTE NÃO POSSUI EXTEND + EQUIPAMENTO INCORRETO | E95: 75981316810 | F95: 46125 | G95: =PROPER(TEXT(F95,"DDD")) -> Seg | H95: 0.41666667 | I95: CARTÃO | J95: ENDEREÇO NOVO: RUA DIMAS MOREIRA DE SÁ, 2851 COMPLEMENTO: CASA 2 CEP: 38405-254 BAIRRO: CUSTÓDIO PEREIRA | K95: <b>ONT = ONT TP LINK 530 // CONECTOR = VERDE.</b> | L95: =IF(B95="MUD END","NÃO","SIM") -> NÃO | M95: - | N95: SIM | O95: - | P95: - | Q95: COMPROVANTE DE ENDEREÇO (CONTRATO DE LOCAÇÃO) EM ANEXO NOME NO COMPROVANTE: LEANDRO DOS SANTOS SILVA (ASSINANTE) | R95: MK END: N/C MK NOMES: DIVINO FERNANDES DE OLIVEIRA CPF:266.583.806-00(LOCADOR)N/C LEANDRO DOS SANTOS SILVA CPF:024.378.955-66(LOCATÁRIO)TITULAR DA CONEXÃO | S95: =IF(F95<TODAY(),"EXECUTADA",IF(F95=TODAY(),"EM EXECUÇÃO",IF(F95=TODAY()+1,"VALIDAR HOJE",IF(F95>TODAY()+1,"VALIDAR DEPOIS","-")))) -> EXECUTADA
A96: MUD END ACSA ALEXANDRE FEITOZA PROT: 2604.7832 PIX (JOSÉ Jr) - MANSOUR | B96: MUD END | D96: VALIDAÇÃO OK ENVIAR AO CADASTRO | E96: 34998336278 | F96: 46125 | G96: =PROPER(TEXT(F96,"DDD")) -> Seg | H96: 0.41666667 | I96: PIX | J96: ENDEREÇO NOVO: RUA RIO JAGUARI, 2029 COMPLEMENTO: CASA UNICA CEP: 38414458 BAIRRO: MANSOUR | K96: <b>ONT = ONT TP LINK 530 // CONECTOR = VERDE.</b> | L96: =IF(B96="MUD END","NÃO","SIM") -> NÃO | M96: - | N96: NÃO | O96: GERLANDIO SOUZA DE ATAIDES (ESPOSO) | P96: 94 99156-6528 | Q96: COMPROVANTE DE ENDEREÇO (CEMIG) EM ANEXO NOME NO COMPROVANTE: ANA MARIA DOS SANTOS (CLIENTE DIZ QUE É LOCADOR) | R96: MK END:N/C MK NOMES: ANA MARIA DOS SANTOS CPF 866.2**.***-**(CLIENTE DIZ QUE É O LOCADOR)N/C | S96: =IF(F96<TODAY(),"EXECUTADA",IF(F96=TODAY(),"EM EXECUÇÃO",IF(F96=TODAY()+1,"VALIDAR HOJE",IF(F96>TODAY()+1,"VALIDAR DEPOIS","-")))) -> EXECUTADA
A97: MUD END EULER DE SOUZA SOARES PROT:2604.8515 DINHEIRO (PEDRO) - SÃO JORGE *PENDENTE COMPROVANTE DE ENDEREÇO* | B97: MUD END | D97: VALIDAÇÃO OK ENVIAR AO CADASTRO | E97: 34974001904 | F97: 46125 | G97: =PROPER(TEXT(F97,"DDD")) -> Seg | H97: 0.41666667 | I97: DINHEIRO | J97: ENDEREÇO NOVO: RUA CÉLIO PONTES, 167 COMPLEMENTO: CASA 1 CEP: 38410050 BAIRRO: SÃO JORGE | K97: <b>ONT = ONT TP LINK 530 // CONECTOR = VERDE.</b> | L97: =IF(B97="MUD END","NÃO","SIM") -> NÃO | M97: - | N97: SIM | O97: - | P97: - | Q97: COMPROVANTE DE ENDEREÇO (CEMIG) EM ANEXO NOME NO COMPROVANTE: RAMIRO NUNES DE OLIVEIRA (EULER ALEGA SER SEU AVÓ) | R97: MK END: N/C MK NOME: RAMIRO NUNES DE OLIVEIRA (EULER ALEGA SER SEU AVÓ) N/C | S97: =IF(F97<TODAY(),"EXECUTADA",IF(F97=TODAY(),"EM EXECUÇÃO",IF(F97=TODAY()+1,"VALIDAR HOJE",IF(F97>TODAY()+1,"VALIDAR DEPOIS","-")))) -> EXECUTADA
A98: MUD END + ALT PLANO MARCIA MARTINS SILVA ANDRADE PROT:2604.8371 ISENTO (VICTOR H.) - SARAIVA **PRÉDIO SEM PRUMADA - ENVIAR TÉCNICO DUPLADO** // PODE ANTECIPAR | B98: MUD END + ALT PLAN | D98: KAROLAYNE / IZABELA | F98: 46125 | G98: =PROPER(TEXT(F98,"DDD")) -> Seg | H98: 0.54166667 | L98: =IF(B98="MUD END","NÃO","SIM") -> SIM | Q98: NOME NO COMPROVANTE: RAMIRO NUNES DE OLIVEIRA (EULER ALEGA SER SEU AVÓ) | S98: =IF(F98<TODAY(),"EXECUTADA",IF(F98=TODAY(),"EM EXECUÇÃO",IF(F98=TODAY()+1,"VALIDAR HOJE",IF(F98>TODAY()+1,"VALIDAR DEPOIS","-")))) -> EXECUTADA
A99: MUD END + ALT PLANO JESSICA TASSIANE ARAUJO GAUDENCIO PROT:2604.8549 ISENTO (RONALD) - JARDIM HOLANDA **PRÉDIO COM PRUMADA** // | B99: MUD END + ALT PLAN | D99: KAROLAYNE / IZABELA | F99: 46125 | G99: =PROPER(TEXT(F99,"DDD")) -> Seg | H99: 0.625 | L99: =IF(B99="MUD END","NÃO","SIM") -> SIM | S99: =IF(F99<TODAY(),"EXECUTADA",IF(F99=TODAY(),"EM EXECUÇÃO",IF(F99=TODAY()+1,"VALIDAR HOJE",IF(F99>TODAY()+1,"VALIDAR DEPOIS","-")))) -> EXECUTADA
A100: MUD END CARLOS EDUARDO GOMES SOARES PROT:2604.3760 CARTAO (PEDRO) - MANSOUR III *PENDENTE MENSALIDADE* | B100: MUD END | D100: PENDENTE 2 MENSALIDADES REMOVIDO DA AGENDA | E100: 34998331025 | F100: 46125 | G100: =PROPER(TEXT(F100,"DDD")) -> Seg | H100: 0.625 | I100: CARTÃO | J100: ENDEREÇO NOVO: RUA WEBERSON ARANTES, 402 COMPLEMENTO: CASA ÚNICA CEP: 38418676 BAIRRO: MANSOUR III | K100: <b>ONT = ONT TP LINK 220 // CONECTOR = VERDE.</b> | L100: =IF(B100="MUD END","NÃO","SIM") -> NÃO | M100: - | N100: SIM | O100: - | P100: - | Q100: COMPROVANTE DE ENDEREÇO (CEMIG) EM ANEXO NOME NO COMPROVANTE: FAUSTO FERNANDES DE OLIVEIRA (DISSE SER O ANTIGO MORADOR) | R100: FAUSTO FERNANDES DE OLIVEIRA - COMPROVANTE - CANCELADO POR INADIMPLENCI (EQUIPMAMENTOS DEVOLVIDOS) - DÉBITOS PENDENTES EM F$1.123,78 | S100: =IF(F100<TODAY(),"EXECUTADA",IF(F100=TODAY(),"EM EXECUÇÃO",IF(F100=TODAY()+1,"VALIDAR HOJE",IF(F100>TODAY()+1,"VALIDAR DEPOIS","-")))) -> EXECUTADA
...
